Workbook

Sheet Mattson LM
A1: Organization: HANWASH
A2: Document: Mattson logic model
A3: Objective: Define the objectives of the program.
A4: Scope: Mattson Program
A5: Reference link: Click here
A6: Version number: 2.5
A7: Version date: January 30, 2024
A8: Notes: The lower level objectives should cause the higher level objectives. Objectives 2230, 2400,2410,2420,2430 are not in the scope of this program.
B11: Type | C11: Description
B12: Ultimate outcome | C12: 1
C13: ='Log frame'!B13 -> Increased access to safe, sustainable and affordable water, sanitation and hygiene (WASH) services in Haiti​.
B14: Intermediate outcomes | C14: 1000 | F14: 2000 | I14: 3000
C15: ='Log frame'!B15 -> Strengthened demand for and management of WASH services in communes. | F15: ='Log frame'!E15 -> Enhanced household access to and use of sustainable, affordable, and safe water, sanitation and hygiene services.​ | I15: Expanded reach and resources leveraged through collective action with other national and international actors.​
B16: Immediate outcomes | C16: 1100 | D16: 1200 | E16: 1300 | F16: 2100 | G16: 2200 | H16: 2300 | I16: 3100 | J16: 3200
C17: ='Log frame'!B17 -> Increased civil society engagement in decision making and implementation of WASH services. | D17: ='Log frame'!C17 -> Improved commune WASH planning and coordination by local authorities.​ | E17: ='Log frame'!D17 -> Improved accountability of service providers to users of WASH services.​ | F17: ='Log frame'!E17 -> Increased household access to sustainable, affordable, and safe drinking water services.​ | G17: ='Log frame'!F17 -> Increased household access to sustainable, affordable, and safe sanitation services.​ | H17: ='Log frame'!G17 -> Increased household access to hygiene services. | I17: Increased government and non-government funding in alignment with HANWASH Core Values. | J17: Increased capacity of DINEPA to regulate the sector and OREPA to oversee and support implementation.
B18: Outputs | C18: 1110 | D18: 1210 | E18: ​1310 | F18: 2110 | G18: 2210 | H18: 2310 | I18: 3110 | J18: 3210
C19: ='Log frame'!B19 -> Support civil society engagement in the WASH sector.​ | D19: ='Log frame'!C19 -> Create or improve commune action plans that focus on water, sanitation and hygiene, and water resource management.​ | E19: ='Log frame'!D19 -> Monitor WASH service performance and satisfaction. | F19: ='Log frame'!E19 -> Develop community managed water points. | G19: ='Log frame'!F19 -> Mobilize communities to achieve Open Defecation Free status | H19: ='Log frame'!G19 -> Train skilled community animators to deliver hygiene trainings and community mobilization.​ | I19: Mobilize and coordinate funding from government and non-government sources in HANWASH program areas in alignment with HANWASH Core Values. | J19: Conduct leadership training of DINEPA and OREPA personnel.
C20: 1120 | D20: 1220 | E20: 1320 | F20: 2120 | G20: 2220 | H20: 2320 | I20: 3120 | J20: 3220
C21: ='Log frame'!B21 -> Train HANWASH Ambassadors & Coordinators and their committees throughout the Caribbean.​ | D21: ='Log frame'!C21 -> Facilitate coordination meetings between commune WASH stakeholders. | E21: ='Log frame'!D21 -> Review service provider performance with stakeholders. | F21: ='Log frame'!E21 -> Rehabilitate and expand professionally operated piped water systems. | G21: ='Log frame'!F21 -> Certify the sustained usage of sanitation services. | H21: Certify the sustained usage of hygiene services. | I21: Mobilize and influence funding from government and non-government sources beyond HANWASH program areas in alignment with HANWASH Core Values. | J21: Provide technical assistance and training to DINEPA and the OREPAs.

Sheet Sheet1
A1: ID | B1: Indicator group | C1: Category | D1: Category_code | E1: Category_code_description | F1: Indicator | G1: Definitions | H1: Units | I1: Baseline Value | J1: Planned Value | K1: current_value | L1: Indicator Type
A2: 1 | C2: Ultimate outcome | D2: 1 | E2: Increased access to safe, sustainable and affordable water, sanitation and hygiene (WASH) services in Haiti​. | F2: - | G2: -
A3: 1000 | C3: Intermediate outcome | D3: 1000 | E3: Strengthened demand for and management of WASH services in communes. | F3: - | G3: -
A4: 1100a | C4: Immediate outcome | D4: 1100 | E4: Increased civil society engagement in decision making and implementation of WASH services. | F4: Percentage of commune-level WASH events that have active Haitian Rotarians participation, measured as a proportion of total reported events. | G4: % of total commune level WASH events reported
A5: 1100b | C5: Immediate outcome | D5: 1100 | E5: Increased civil society engagement in decision making and implementation of WASH services. | F5: % of total number of participants in WASH project team meeting which are Haitian rotarians (disaggregated by RC) (Host club should set the target) | G5: % of total number of participants in WASH project team meeting
A6: 1110a | C6: Outputs | D6: 1110 | E6: Support civil society engagement in the WASH sector.​ | F6: Total number of field visits conducted quarterly by Rotarians in the intervention communities. | G6: # of field visits
A7: 1200a | C7: Immediate outcome | D7: 1200 | E7: Improved commune WASH planning and coordination by local authorities.​ | F7: Percentage of the interventions that have received formal approval/assignment from the Mayors offices through a demand letter or other written documents which have been implemented or are in-process by HANWASH or its partners. The approved interventions are subsets of the commune action plans which are assigned to HANWASH or its partners by the Mayor's Offices. | G7: % of implemented activities
A8: 1210a | C8: Outputs | D8: 1210 | E8: Create or improve commune action plans that focus on water, sanitation and hygiene, and water resource management.​ | F8: Number of communes with comprehensive action plans that explicitly address all four WASH aspects: Water, Sanitation, Hygiene, and Water Resources Management. | G8: communes
A9: 1220a | C9: Outputs | D9: 1220 | E9: Facilitate coordination meetings between commune WASH stakeholders. | F9: Number of WASH planning and coordination events conducted with DINEPA and municipal officials per month, fostering collaboration and alignment. | G9: events/month
A10: 1300a | C10: Immediate outcome | D10: 1300 | E10: Improved accountability of service providers to users of WASH services.​ | F10: A service provider is defined as the management structure in charge of a water system (“SAEP”) or a community-managed well (“CPE”). This indicator measures the % of service providers regularly (i.e. monthly) submitting reports to DINEPA and local authorities, according to the DINEPA's requirements in terms of indicators to be captured and data to be shared. | G10: % of the total number of service providers which received the HANWASH intervention in the target communes
A11: 1300b | C11: Immediate outcome | D11: 1300 | E11: Improved accountability of service providers to users of WASH services.​ | F11: Percentage of intervention service providers that have a score of accountability of 11 out of 11. The service provider is 100% accountable if: 1) CPE or Operator team meets regularly (see OREPA bylaws) 2) CPE or Operator meets with community regularly (see OREPA bylaws) 3) CPE or Operator signed bylaws with OREPA and apply them 4) Water usage fees are collected on a monthly basis from the subscribers 5) Deposits are made on a monthly basis on the bank account and records are available; 6) Reports are submitted to OREPA and the local authorities on a monthly basis 7) Water treatment is done regularly, in alignment with OREPA's requirements 8) Water potability test is done at the water points or the water system regularly, in alignment with OREPA's requirements (at least once every quarter for the community water points) 9) Number of days out of service in the event of a water infrastructure breakdown doesn't exceed five days. 10) The service provider pays monthly to OREPA a percentage of the total revenue being collected (see OREPA bylaws) 11) Election is held every three years to renew the CPE members | G11: % of intervention water points
A12: 1300c | C12: Immediate outcome | D12: 1300 | E12: Improved accountability of service providers to users of WASH services.​ | F12: This indicator measures the proportion of the water customers from the intervention communes which are satisfied with the quality, affordability and reliability of the WASH services provided | G12: % of households connected to the water systems
A13: 1310a | C13: Outputs | D13: 1310 | E13: Monitor WASH service performance and satisfaction. | F13: This indicator measures how long it takes on average for the service providers to resolve breakdown of the water infrastructure. The indicator is disaggregated by type of management structure in charge of the water infrastructures: CPEs, CAEPA/CTE/OP. | G13: Days
A14: 1310b | C14: Outputs | D14: 1310 | E14: Monitor WASH service performance and satisfaction. | F14: This indicator measures the average number of days of drinking water service provided to the users during the month by the service providers. The indicator is disaggregated by type of management structure in charge of the water infrastructures: CPEs, CAEPA/CTE/OP. | G14: Days
A15: 1310c | C15: Outputs | D15: 1310 | E15: Monitor WASH service performance and satisfaction. | F15: This indicator measures the number of on-site inspection visits conducted annually by OREPA in the intervention communes | G15: on-site inspection visits
... A17: 1320a | C17: Outputs | D17: 1320 | E17: Review service provider performance with stakeholders. | F17: This indicator measures the number of communes within the program area that have conducted at least one formal, documented annual review meeting in the past 12 months to assess the performance of water and sanitation service providers. The review must involve key stakeholders, including the Commune Committee (CASEC/ASEC or local authorities), users (e.g., representatives of community water users), service providers (e.g., water system operators), and implementing partners (e.g., NGOs, donors, or government agencies involved in WASH service delivery). Key Criteria for Counting a Commune as Having Met the Indicator: 1) A service provider performance review meeting was held within the last 12 months. 2) The meeting was convened or co-organized by the commune authority or another recognized coordinating body. 3) Representatives from all five stakeholder groups (OREPA, Commune Committee, users, service providers, implementing partners) were invited and at least three attended. 4) The meeting included a structured agenda covering topics such as service quality, financial performance, user satisfaction, and challenges. 5) Meeting minutes or a summary report was produced and made available to participants. | G17: communes
A18: 2000 | C18: Intermediate outcome | D18: 2000 | E18: Enhanced household access to and use of sustainable, affordable, and safe water, sanitation and hygiene services.​ | F18: - | G18: -
A19: 2100b | C19: Immediate outcome | D19: 2100 | E19: Increased household access to sustainable, affordable, and safe drinking water services.​ | F19: Percentage of population in intervention communes with access to at least basic drinking water service, defined as an improved water source within 30 minutes round trip. "...at least basic drinking water service": 1) Improved water source (according to the JMP classification) 2) Within 30 min round trip Note: This also includes basic and safely managed water service. | G19: % of people in the commune
A20: 2100c | C20: Immediate outcome | D20: 2100 | E20: Increased household access to sustainable, affordable, and safe drinking water services.​ | F20: Percentage of population in intervention communes with access to safely managed drinking water service, defined as an improved water source accessible on premises, available when needed, and free from contamination. "Safely managed drinking water service": 1) Improved water source (according to the JMP classification) 2) Accessible on premises 3) Available when needed 4) Free from E. Coli and priority contaminants | G20: % of people in the commune
A21: 2100d | C21: Immediate outcome | D21: 2100 | E21: Increased household access to sustainable, affordable, and safe drinking water services.​ | F21: Percentage of intervention water points that are functioning, potable, and financially sustainable (balanced or surplus budget) after 2 years of operation. 1a) Functional: Water point is in good working condition and regularly provides water according the specifications in the original design. OR 1b) Partially functional but in need of repair: Water point provides water on a regular basis (possibly in a reduced capacity) but repairs are needed due to some maintenance issue or change in conditions at the site. 2) "Potable": Free from E. Coli and priority contaminants, as measured by quarterly water potability tests performed by the Water Point Committee. 3) "financially sustainable (balanced or surplus budget)": See PPT presentation with definition of financial sustainability of the community-managed water points. 4) "after 2 years": Two years from the inauguration date of each intervention water point. | G21: % of intervention water points
A22: 2110a | C22: Outputs | D22: 2110 | E22: Develop community managed water points. | F22: Number of people in intervention communes gaining access to basic drinking water service through community-managed water points built or rehabilitated by HANWASH and its partners. "Basic drinking water service": 1) Improved water source (according to the JMP classification) 2) Within 30 min round trip 3) [Household level] | G22: people
A23: 2120a | C23: Outputs | D23: 2120 | E23: Rehabilitate and expand professionally operated piped water systems. | F23: Number of people newly provided with safely managed drinking water service, meeting WHO/UNICEF Joint Monitoring Programme (JMP) criteria. "Safely managed drinking water service": 1) Improved water source (According to the JMP classification) 2) Available on premises 3) Available when needed 4) Free from E. Coli and priority contaminants, as measured by quarterly water quality testing performed by the Water Points Committees. | G23: people
A24: 2200a | C24: Immediate outcome | D24: 2200 | E24: Increased household access to sustainable, affordable, and safe sanitation services.​ | F24: Percentage of intervention communities verified as Open Defecation Free (ODF), by the commune WASH committee. "Verified ODF": 0) [Verification conducted by commune WASH committee] 1) 100% of households have a toilet that has been used at least once 2) Toilets meet the minimum standards of hygiene, privacy, and security and are in alignment with DINEPA's minimum standards 3) Areas of defecation identified during contact visits, reported no evidence of fecal matter 4) Schools attended by 80% of children comply with hygiene standards 5) Main market frequented by the population has a usable sanitary block or a formal step has been undertaken for this purpose 6) There is a willingness of the community to maintain a state of ODF | G24: % of total # of intervention communities
A25: 2200b | C25: Immediate outcome | D25: 2200 | E25: Increased household access to sustainable, affordable, and safe sanitation services.​ | F25: Percentage of intervention communities that have been certified as Open Defecation Free (ODF) by the Communal Committee and OREPA, maintaining verified ODF status for at least one year. | G25: % of total # of intervention communities
A26: 2200c | C26: Immediate outcome | D26: 2200 | E26: Increased household access to sustainable, affordable, and safe sanitation services.​ | F26: Percentage of population in intervention communes with access to at least basic sanitation service, defined as improved and unshared facilities. "...at least basic sanitation service": Basic 1) Improved (According to the JMP classification) 2) Unshared 3) [Household level] Note: Includes basic and safely managed sanitation service. | G26: % of total # of people in the commune
A27: 2210a | C27: Outputs | D27: 2210 | E27: Mobilize communities to achieve Open Defecation Free status | F27: Number of people who newly gained access to basic sanitation service in the intervention communes, as a result of HANWASH interventions. "Basic sanitation service": 1) Improved (according to the JMP classification) 2) Unshared 3) [Household level] | G27: people
A28: 2230a | C28: Outputs | D28: 2230 | E28: Construct public latrines. | F28: Number of public latrines constructed, improving sanitation access in communal areas. | G28: Public toilet blocks
A29: 2300a | C29: Immediate outcome | D29: 2300 | E29: Increased household access to hygiene services. | F29: Percentage of population in intervention communes with access to at least basic hygiene service, defined as presence of a handwashing facility with soap and water on premises. "...at least basic hygiene service" (according to the JMP classification): 1) Presence of a Hanwashing facility on premises 2) Presence of soap and water Notes: Also include people with access to hygiene services higher than basic. (we don't know yet what this looks like) | G29: % of people within intervention communities
A30: 2310a | C30: Outputs | D30: 2310 | E30: Train skilled community animators to deliver hygiene trainings and community mobilization.​ | F30: Number of community animators/coaches trained to provide leadership and WASH training to people in the intervention communities. | G30: animators/coaches
... A40: 2430b | C40: Outputs | D40: 2430 | E40: Work with (local authorities, civil society) to ensure access to soap or alcohol-based handrub at schools and healthcare facilities. | F40: Number of healthcare facilities newly provided with basic hygiene services in the intervention communes, as a result of HANWASH and partners' interventions, meeting WHO/UNICEF JMP criteria for healthcare facilities. "Basic hygiene": ...At points of care 1) Facilities present 2) Soap and water or alcohol based hand rub present ...At toilets 1) Within 5 m of toilets 2) Facilities present 3) Soap and water present | G40: healthcare facilities
A41: 3000 | C41: Intermediate outcome | D41: 3000 | E41: Expanded reach and resources leveraged through collective action with other national and international actors.​ | F41: - | G41: -
A42: 3100a | C42: Immediate outcome | D42: 3100 | E42: Increased government and non-government funding in alignment with HANWASH Core Values. | F42: Cumulative amount of money (in USD) committed to projects aligned with HANWASH Core Values: local leadership, collaboration, systematic approach, impact, and commitment. Aligned with HANWASH Core Values: **LOCALLY LED** We strengthen community participation in governance of WASH infrastructure and services. **COLLABORATIVE** Volunteers, government authorities, and partners are meaningfully engaged, and a MOU is signed among the parties. ### **SYSTEMATIC** We will be thoughtful and consistent in planning, doing, and improving our work.** **IMPACTFUL** Sustainability is a key metric of our success. **COMMITTED** We will not stop until the job is done. | G42: USD
A43: 3100b | C43: Immediate outcome | D43: 3100 | E43: Increased government and non-government funding in alignment with HANWASH Core Values. | F43: Percentage of committed funds that have been spent, calculated as (Cumulative_amount_spent / Cumulative_amount_committed) * 100. | G43: % of amount committeed
A44: 3110a | C44: Outputs | D44: 3110 | E44: Mobilize and coordinate funding from government and non-government sources in HANWASH program areas in alignment with HANWASH Core Values. | F44: Cumulative amount of money (in USD) spent by external (non-rotarian) actors within HANWASH project areas, aligned with HANWASH Core Values. | G44: USD
A45: 3120a | C45: Outputs | D45: 3120 | E45: Mobilize and influence funding from government and non-government sources beyond HANWASH program areas in alignment with HANWASH Core Values. | F45: Cumulative amount of money (in USD) spent by external (non-rotarian) actors beyond HANWASH project areas but still within the WASH sector and aligned with HANWASH Core Values, extending impact. | G45: USD
A46: 3200a | C46: Immediate outcome | D46: 3200 | E46: Increased capacity of DINEPA to regulate the sector and OREPA to oversee and support implementation. | F46: Percentage of implementing partners in HANWASH program areas who have signed the DINEPA Accord Cadre, ensuring alignment with national standards. (Number of IPs who have signed the Accord Cadre / Total number of IPs in HANWASH program areas) x 100 | G46: % of implementing partners in HANWASH program areas
A47: 3220a | C47: Outputs | D47: 3220 | E47: Provide technical assistance and training to DINEPA and the OREPAs. | F47: Number of technical trainings provided for DINEPA priority areas, focusing on key topics such as unified national tariff methodology and ODF certification. Priorities areas for 2023-24: Unified national tariff methodology & ODF certification. Priorities areas for 2024-2025: ? Priorities areas for 2025-2026: ? | G47: trainings

Sheet Indicator framework-Revised
A1: Organization: HANWASH | E1: Legend
A2: Document: Indicator framework | E2: TBD' To be determined | F2: ="'-' Not applicable" -> '-' Not applicable
A3: Objective: Define indicators to measure progress towards each objective.
A4: Scope: HANWASH programs | E4: Objective types | F4: Description
A5: Reference link: This document | E5: Ultimate outcome | F5: The highest level objective of HANWASH. These are not directly measureable by SMART indicators, but measured indirectly via indicators of their component Intermediate Outcomes.
A6: Version number: 3 | E6: Intermediate outcome | F6: The component objectives of the HANWASH ultimate outcome. These are not directly measureable by SMART indicators, but measured indirectly via indicators of their component Intermediate Outcomes.
A7: Version date: June 30, 2025 | E7: Immediate outcome | F7: The higher level objective that HANWASH seeks to achieve, which are able to be measured directly by SMART indicators. Indicators measuring these outcomes are typically expressed as a percent, which are harder to measure, but builds the context into the measure.
A8: Notes: SMART indicators are indicators which are specific, measureable, achievable, relevant, and time-bound. | E8: Output | F8: The lower level objective that HANWASH seeks to achieve. Indicators measuring these outcomes are typically expressed as a number, which is easier to measure, but also easier to take out of context.
A10: Objective | D10: Indicator | K10: Data collection | P10: Commune validation | R10: Data validation and Reporting | V10: Notes
A11: Type | B11: Code | C11: Description | D11: Code_index | E11: Description | F11: Definitions | G11: Units | H11: Status | I11: Program | J11: (Dis)Aggregation | K11: Source | L11: Enumerator | M11: Type of data collection | N11: Frequency | O11: Visualization | P11: Data source | Q11: Data collection | R11: Source | S11: Data Validator | T11: Reporting Frequency | U11: Visualization
A12: Ultimate outcome | B12: 1 | C12: ='Log frame'!B13 -> Increased access to safe, sustainable and affordable water, sanitation and hygiene (WASH) services in Haiti​. | D12: - | E12: - | F12: - | G12: - | H12: - | I12: ="Mattson" -> Mattson | J12: - | K12: - | L12: - | N12: - | O12: - | P12: - | Q12: - | R12: - | S12: - | T12: - | U12: - | V12: This objective is split into its component objectives and measured via their indicators
A13: Intermediate outcome | B13: 1000 | C13: ='Log frame'!B15 -> Strengthened demand for and management of WASH services in communes. | D13: - | E13: - | F13: - | G13: - | H13: - | I13: ="Mattson" -> Mattson | J13: - | K13: - | L13: - | N13: - | O13: - | P13: - | Q13: - | R13: - | S13: - | T13: - | U13: - | V13: This objective is split into its component objectives and measured via their indicators
A14: Immediate outcome | B14: 1100 | C14: ='Log frame'!B17 -> Increased civil society engagement in decision making and implementation of WASH services. | D14: 1100a | E14: % of on-site commune WASH events with Haitian Rotarian participation | F14: Percentage of commune-level WASH events that have active Haitian Rotarians participation, measured as a proportion of total reported events. | G14: % of total commune level WASH events reported | H14: In service - Needs training | I14: ="Mattson" -> Mattson | J14: Event type, participant group, date, commune | K14: Implementation event tracking form | L14: M&E RC Focal points | M14: Secondary | N14: Monthly | O14: Implementation monitoring console | R14: Interview with the Mayors and the RC Presidents | S14: HANWASH M&E Manager | T14: Semi-annually | U14: Implementation monitoring console | V14: System validation consists of an exhaustive desk review of both the PMO and Rotarians forms.
A15: Immediate outcome | B15: 1100 | C15: Increased civil society engagement in decision making and implementation of WASH services. | D15: 1100b | E15: Proportion (%) of paricipants in the virtual WASH projects meetings which are Haitian rotarians | F15: % of total number of participants in WASH project team meeting which are Haitian rotarians (disaggregated by RC) (Host club should set the target) | G15: % of total number of participants in WASH project team meeting | H15: Not started | I15: Mattson | J15: Event type, participant group, date, commune | K15: Implementation event tracking form | L15: M&E RC Focal points | M15: Secondary | N15: Monthly | O15: Implementation monitoring console | P15: Review of existing data | Q15: HANWASH M&E Manager | R15: Review of existing data from virtual meeting record. | S15: HANWASH M&E Manager | T15: Semi-annually | U15: Implementation monitoring console
A16: Outputs | B16: 1110 | C16: Support civil society engagement in the WASH sector.​ | D16: 1110a | E16: # of field visits conducted quarterly by Rotarians in the intervention communities | F16: Total number of field visits conducted quarterly by Rotarians in the intervention communities. | G16: # of field visits | H16: In service - Needs training | I16: ="Mattson" -> Mattson | J16: Event type, participant group, date, commune | K16: Implementation event tracking form | L16: M&E RC Focal points | M16: Secondary | N16: Monthly | O16: Implementation monitoring console | R16: Review of existing data | S16: HANWASH M&E Manager | T16: Semi-annually | U16: Implementation monitoring console | V16: System validation consists of an exhaustive desk review of both the PMO and Rotarians forms.
A17: Immediate outcome | B17: 1200 | C17: ='Log frame'!C17 -> Improved commune WASH planning and coordination by local authorities.​ | D17: 1200a | E17: % of approved interventions implemented in alignment with Commune Action Plans | F17: Percentage of the interventions that have received formal approval/assignment from the Mayors offices through a demand letter or other written documents which have been implemented or are in-process by HANWASH or its partners. The approved interventions are subsets of the commune action plans which are assigned to HANWASH or its partners by the Mayor's Offices. | G17: % of implemented activities | H17: In service - Needs mods | I17: ="Mattson" -> Mattson | J17: Date, commune | K17: Activities form | L17: Mayors | M17: Secondary | N17: Semi-annually | O17: Project monitoring console | P17: Commune action plan | Q17: Commune WASH committee | R17: Review of existing data | S17: HANWASH M&E Manager | T17: Semi-annually | U17: Project monitoring console | V17: It's critical that "Activities" planned by HANWASH correspond to those in the commune action plan in the system.
A18: Outputs | B18: 1210 | C18: ='Log frame'!C19 -> Create or improve commune action plans that focus on water, sanitation and hygiene, and water resource management.​ | D18: 1210a | E18: # of communes with action plans that explicitly include each W,S,H,WRM aspect (water, sanitation, hygiene, water resources management) | F18: Number of communes with comprehensive action plans that explicitly address all four WASH aspects: Water, Sanitation, Hygiene, and Water Resources Management. | G18: communes | H18: In service - Needs mods | I18: ="Mattson" -> Mattson | J18: Date, commune | K18: Activities form | L18: Mayors | M18: Secondary | N18: Annually | O18: Project monitoring console | R18: Review of existing data | S18: HANWASH M&E Manager | T18: Annually | U18: Project monitoring console | V18: System validation consists of an exhaustive desk review of reported data
A19: Outputs | B19: 1220 | C19: ='Log frame'!C21 -> Facilitate coordination meetings between commune WASH stakeholders. | D19: 1220a | E19: # of WASH planning and coordination events with DINEPA and municipal officials | F19: Number of WASH planning and coordination events conducted with DINEPA and municipal officials per month, fostering collaboration and alignment. | G19: events/month | H19: In service - Needs training | I19: ="Mattson" -> Mattson | J19: Event type, participant group, date, commune | K19: Implementation event tracking form | L19: Mayors & Partner of Implementation | M19: Secondary | N19: Monthly | O19: Implementation monitoring console | R19: Review of existing data | S19: HANWASH M&E Manager | T19: Semi-annually | U19: Implementation monitoring console | V19: System validation consists of a sampled desk review of reported data
A20: Immediate outcome | B20: 1300 | C20: ='Log frame'!D17 -> Improved accountability of service providers to users of WASH services.​ | D20: 1300a | E20: % of service providers under HANWASH initiative monitored according to DINEPA/OREPA guidelines as accepted by the Mayor's Office | F20: A service provider is defined as the management structure in charge of a water system (“SAEP”) or a community-managed well (“CPE”). This indicator measures the % of service providers regularly (i.e. monthly) submitting reports to DINEPA and local authorities, according to the DINEPA's requirements in terms of indicators to be captured and data to be shared. | G20: % of the total number of service providers which received the HANWASH intervention in the target communes | H20: In service - Needs mods | I20: Mattson | J20: Water point/system, date, commune | K20: Water point survey and SAEP monthly report | L20: OREPA focal points | M20: Secondary | N20: Monthly | O20: Implementation monitoring console | R20: Water point survey - Audit | S20: OREPA Focal Points & HANWASH M&E Manager | T20: Semi-annually | U20: Third party audit console (TBD) | V20: The reporting and system validation forms are the same, just different deployments carried out by different stakeholders. Reporting: PMO. Validation: Third party contractor.
A21: Immediate outcome | B21: 1300 | C21: ='Log frame'!D17 -> Improved accountability of service providers to users of WASH services.​ | D21: 1300b | E21: % of intervention service providers which are 100% accountable per DINEPA/OREPA and the Mayor's requirements | F21: Percentage of intervention service providers that have a score of accountability of 11 out of 11. The service provider is 100% accountable if: 1) CPE or Operator team meets regularly (see OREPA bylaws) 2) CPE or Operator meets with community regularly (see OREPA bylaws) 3) CPE or Operator signed bylaws with OREPA and apply them 4) Water usage fees are collected on a monthly basis from the subscribers 5) Deposits are made on a monthly basis on the bank account and records are available; 6) Reports are submitted to OREPA and the local authorities on a monthly basis 7) Water treatment is done regularly, in alignment with OREPA's requirements 8) Water potability test is done at the water points or the water system regularly, in alignment with OREPA's requirements (at least once every quarter for the community water points) 9) Number of days out of service in the event of a water infrastructure breakdown doesn't exceed five days. 10) The service provider pays monthly to OREPA a percentage of the total revenue being collected (see OREPA bylaws) 11) Election is held every three years to renew the CPE members | G21: % of intervention water points | H21: In service - Needs mods | I21: ="Mattson" -> Mattson | J21: Water point, date, commune | K21: Accountability Evaluation Form (TBD) | L21: Mayors & OREPA focal points | M21: Secondary | N21: Annually | O21: Implementation monitoring console | P21: Water point survey | R21: Water point survey - Audit | S21: OREPA Focal Points & HANWASH M&E Manager | T21: Annually | U21: Third party audit console (TBD) | V21: The reporting and system validation forms are the same, just different deployments carried out by different stakeholders. Reporting: PMO. Validation: Third party contractor.
A22: Immediate outcome | B22: 1300 | C22: Improved accountability of service providers to users of WASH services.​ | D22: 1300c | E22: % of users being satisfied with the quality, affordability and reliability of the WASH services provided | F22: This indicator measures the proportion of the water customers from the intervention communes which are satisfied with the quality, affordability and reliability of the WASH services provided | G22: % of households connected to the water systems | H22: Not started | I22: Mattson | J22: Water point, commune | K22: Subscribers Satisfaction Survey (TBD) | L22: Water Service provider | M22: Primary (on-site survey) | N22: Annually | O22: Implementation monitoring console | P22: Water point survey - Audit | Q22: Third party contractor | R22: Field data collection | S22: OREPA Focal Points & HANWASH M&E Manager | T22: Annually | U22: Implementation monitoring console
A23: Outputs | B23: 1310 | C23: ='Log frame'!D19 -> Monitor WASH service performance and satisfaction. | D23: 1310a | E23: Average number of days to resolve breakdown of the water infrastructures | F23: This indicator measures how long it takes on average for the service providers to resolve breakdown of the water infrastructure. The indicator is disaggregated by type of management structure in charge of the water infrastructures: CPEs, CAEPA/CTE/OP. | G23: Days | H23: Not started | I23: ="Mattson" -> Mattson | J23: Water system, date, commune | K23: SAEP monthly report, Water point survey | L23: Water service provider | M23: Secondary | N23: Monthly | O23: Implementation monitoring console | R23: Review of existing data | S23: OREPA Focal Points & HANWASH M&E Manager | T23: Semi-annually | U23: Implementation monitoring console | V23: System validation consists of a sampled desk review of reported data
A24: Outputs | B24: 1310 | C24: =C23 -> Monitor WASH service performance and satisfaction. | D24: 1310b | E24: Average number of days of drinking water service provided during the month by the service providers | F24: This indicator measures the average number of days of drinking water service provided to the users during the month by the service providers. The indicator is disaggregated by type of management structure in charge of the water infrastructures: CPEs, CAEPA/CTE/OP. | G24: Days | H24: Not started | I24: ="Mattson" -> Mattson | J24: Water system, date, commune | K24: SAEP monthly report, Water point survey | L24: Water service provider | M24: Secondary | N24: Monthly | O24: Implementation monitoring console | R24: Review of existing data | S24: OREPA Focal Points & HANWASH M&E Manager | T24: Semi-annually | U24: Implementation monitoring console | V24: System validation consists of a sampled desk review of reported data
A25: Outputs | B25: 1310 | C25: =C24 -> Monitor WASH service performance and satisfaction. | D25: 1310c | E25: Number of on-site inspection visits conducted annually by OREPA in the intervention communes | F25: This indicator measures the number of on-site inspection visits conducted annually by OREPA in the intervention communes | G25: on-site inspection visits | K25: OREPA's field inspection reports (TBD) | L25: OREPA focal points | N25: Quarterly | R25: Review of OREPA's field inspection reports | S25: OREPA Focal Points | T25: Semi-annually
A26: Outputs | B26: 1310 | C26: =C25 -> Monitor WASH service performance and satisfaction. | D26: 1310d | E26: Water fee collection rate (disaggregated by type of service providers) | F26: The percentage of the total water user fees that were successfully collected from subscribers by the service providers within a quarter, compared to the total amount billed or expected during that period. This indicator is disaggregated by type of service provider (CPE, professional operator, CAEPA, CTE). | G26: % of total amount of water fees billed or expected during the quarter | J26: CPE, professional operator, CAEPA, CTE | K26: SAEP monthly report, Water point survey | L26: Water Service provider | M26: Secondary | N26: Monthly | S26: OREPA Focal Points & HANWASH M&E Manager | T26: Semi-annually
A27: Outputs | B27: 1320 | C27: ='Log frame'!D21 -> Review service provider performance with stakeholders. | D27: 1320a | E27: # of communes which have held an annual service provider review with key stakeholders in the last year | F27: This indicator measures the number of communes within the program area that have conducted at least one formal, documented annual review meeting in the past 12 months to assess the performance of water and sanitation service providers. The review must involve key stakeholders, including the Commune Committee (CASEC/ASEC or local authorities), users (e.g., representatives of community water users), service providers (e.g., water system operators), and implementing partners (e.g., NGOs, donors, or government agencies involved in WASH service delivery). Key Criteria for Counting a Commune as Having Met the Indicator: 1) A service provider performance review meeting was held within the last 12 months. 2) The meeting was convened or co-organized by the commune authority or another recognized coordinating body. 3) Representatives from all five stakeholder groups (OREPA, Commune Committee, users, service providers, implementing partners) were invited and at least three attended. 4) The meeting included a structured agenda covering topics such as service quality, financial performance, user satisfaction, and challenges. 5) Meeting minutes or a summary report was produced and made available to participants. | G27: communes | H27: In service - Needs mods | I27: ="Mattson" -> Mattson | J27: Water system, date, commune | K27: SAEP monthly report | L27: Mayors & Water service provider | M27: Secondary | N27: Annually | O27: Implementation monitoring console | R27: - | S27: OREPA Focal Points & HANWASH M&E Manager | T27: Annually | U27: Implementation monitoring console | V27: System validation consists of a sampled desk review of reported data
A28: Intermediate outcome | B28: 2000 | C28: ='Log frame'!E15 -> Enhanced household access to and use of sustainable, affordable, and safe water, sanitation and hygiene services.​ | D28: - | E28: - | F28: - | G28: - | H28: - | I28: ="Mattson" -> Mattson | J28: - | K28: - | L28: - | N28: - | O28: - | P28: - | Q28: - | R28: - | S28: - | T28: - | U28: - | V28: This objective is split into its component objectives and measured via their indicators
A29: Immediate outcome | B29: 2100 | C29: ='Log frame'!E17 -> Increased household access to sustainable, affordable, and safe drinking water services.​ | D29: 2100b | E29: % of population in intervention communes with at least basic drinking water service | F29: Percentage of population in intervention communes with access to at least basic drinking water service, defined as an improved water source within 30 minutes round trip. "...at least basic drinking water service": 1) Improved water source (according to the JMP classification) 2) Within 30 min round trip Note: This also includes basic and safely managed water service. | G29: % of people in the commune | H29: In service - Needs training | I29: ="Mattson" -> Mattson | J29: Community, date, commune, improved water source, within 30 min round trip | K29: Household WASH survey | L29: Partner of implementation | M29: Primary (on-site survey) | N29: Annually | O29: Implementation monitoring console | R29: Household survey - Audit | S29: OREPA Focal Points & HANWASH M&E Manager | T29: Annually | U29: Third party audit console (TBD) | V29: The system validation form is more detailed and precise, but it is a sampled check on the reporting system
A30: Immediate outcome | B30: 2100 | C30: ='Log frame'!E17 -> Increased household access to sustainable, affordable, and safe drinking water services.​ | D30: 2100c | E30: % of population in intervention communes with safely managed drinking water service | F30: Percentage of population in intervention communes with access to safely managed drinking water service, defined as an improved water source accessible on premises, available when needed, and free from contamination. "Safely managed drinking water service": 1) Improved water source (according to the JMP classification) 2) Accessible on premises 3) Available when needed 4) Free from E. Coli and priority contaminants | G30: % of people in the commune | H30: In service - Needs training | I30: ="Mattson" -> Mattson | J30: Community, date, commune, Improved water source, accessible on premises, available when needed, free from E. Coli and priority contaminants | K30: Household WASH survey | L30: Partner of implementation | M30: Primary (on-site survey) | N30: Annually | O30: Implementation monitoring console | R30: Household survey - Audit | S30: OREPA Focal Points & HANWASH M&E Manager | T30: Annually | U30: Third party audit console (TBD) | V30: The system validation form is more detailed and precise, but it is a sampled check on the reporting system
A31: Immediate outcome | B31: 2100 | C31: ='Log frame'!E17 -> Increased household access to sustainable, affordable, and safe drinking water services.​ | D31: 2100d | E31: % of intervention water points which are functional, potable, and have a balanced budget or a budget with surplus after 2 years | F31: Percentage of intervention water points that are functioning, potable, and financially sustainable (balanced or surplus budget) after 2 years of operation. 1a) Functional: Water point is in good working condition and regularly provides water according the specifications in the original design. OR 1b) Partially functional but in need of repair: Water point provides water on a regular basis (possibly in a reduced capacity) but repairs are needed due to some maintenance issue or change in conditions at the site. 2) "Potable": Free from E. Coli and priority contaminants, as measured by quarterly water potability tests performed by the Water Point Committee. 3) "financially sustainable (balanced or surplus budget)": See PPT presentation with definition of financial sustainability of the community-managed water points. 4) "after 2 years": Two years from the inauguration date of each intervention water point. | G31: % of intervention water points | H31: In service - Needs mods | I31: ="Mattson" -> Mattson | J31: Date, commune | K31: Water point survey | L31: Partner of implementation | M31: Primary (on-site survey) | N31: Semi-annually | O31: Implementation monitoring console | R31: Water point survey - Audit | S31: OREPA Focal Points & HANWASH M&E Manager | T31: Annually | U31: Third party audit console (TBD) | V31: The reporting and system validation forms are the same, just different deployments carried out by different stakeholders. Reporting: PMO. Validation: Third party contractor.
A32: Outputs | B32: 2110 | C32: ='Log frame'!E19 -> Develop community managed water points. | D32: 2110a | E32: # of people added to basic drinking water service through community managed water points | F32: Number of people in intervention communes gaining access to basic drinking water service through community-managed water points built or rehabilitated by HANWASH and its partners. "Basic drinking water service": 1) Improved water source (according to the JMP classification) 2) Within 30 min round trip 3) [Household level] | G32: people | H32: In service - Needs training | I32: ="Mattson" -> Mattson | J32: Water point, gender, age category, improved water source, within 30 min round trip | K32: Water point survey | L32: Partner of implementation | M32: Primary (on-site survey) | N32: Semi-annually | O32: Implementation monitoring console | R32: Household survey - Audit | S32: HANWASH M&E Manager | T32: Semi-annually | U32: Third party audit console (TBD) | V32: The system validation form is more detailed and precise, but it is a sampled check on the reporting system
A33: Outputs | B33: 2120 | C33: ='Log frame'!E21 -> Rehabilitate and expand professionally operated piped water systems. | D33: 2120a | E33: # of people added to safely managed drinking water service through water systems newly created or rehabilitated in the intervention communes | F33: Number of people newly provided with safely managed drinking water service, meeting WHO/UNICEF Joint Monitoring Programme (JMP) criteria. "Safely managed drinking water service": 1) Improved water source (According to the JMP classification) 2) Available on premises 3) Available when needed 4) Free from E. Coli and priority contaminants, as measured by quarterly water quality testing performed by the Water Points Committees. | G33: people | H33: In service - Needs training | I33: ="Mattson" -> Mattson | J33: Newly created or rehabilitated Water systems, gender, category of subscribers | K33: SAEP monthly report | L33: Partner of implementation | M33: Secondary | N33: Semi-annually | O33: Implementation monitoring console | R33: Household survey - Audit | S33: HANWASH M&E Manager | T33: Semi-annually | U33: Third party audit console (TBD) | V33: The system validation form is more detailed and precise, but it is a sampled check on the reporting system
A34: Immediate outcome | B34: 2200 | C34: ='Log frame'!F17 -> Increased household access to sustainable, affordable, and safe sanitation services.​ | D34: 2200a | E34: % of intervention communities which are verified ODF (Open Defecation Free) | F34: Percentage of intervention communities verified as Open Defecation Free (ODF), by the commune WASH committee. "Verified ODF": 0) [Verification conducted by commune WASH committee] 1) 100% of households have a toilet that has been used at least once 2) Toilets meet the minimum standards of hygiene, privacy, and security and are in alignment with DINEPA's minimum standards 3) Areas of defecation identified during contact visits, reported no evidence of fecal matter 4) Schools attended by 80% of children comply with hygiene standards 5) Main market frequented by the population has a usable sanitary block or a formal step has been undertaken for this purpose 6) There is a willingness of the community to maintain a state of ODF | G34: % of total # of intervention communities | H34: In service - Needs training | I34: ="Mattson" -> Mattson | J34: Date, commune | K34: ODF verification and certification Form | L34: Commune WASH committee | M34: Primary (on-site survey) | N34: Semi-annually | O34: Implementation monitoring console | R34: Household survey - Audit | S34: Mayors & HANWASH M&E Manager | T34: Semi-annually | U34: Third party audit console (TBD) | V34: The system validation form is more detailed and precise, but it is a sampled check on the reporting system
A35: Immediate outcome | B35: 2200 | C35: =C34 -> Increased household access to sustainable, affordable, and safe sanitation services.​ | D35: 2200b | E35: % of "intervention" communities which are certified ODF (Open Defecation Free) | F35: Percentage of intervention communities that have been certified as Open Defecation Free (ODF) by the Communal Committee and OREPA, maintaining verified ODF status for at least one year. | G35: % of total # of intervention communities | H35: In service - Needs training | I35: ="Mattson" -> Mattson | J35: Community, date, commune | K35: ODF verification and certification Form | L35: Commune WASH committee & OREPA Focal Points | M35: Primary (on-site survey) | N35: Annually | O35: Implementation monitoring console | R35: Household survey - Audit | S35: OREPA Focal Points & HANWASH M&E Manager | T35: Annually | U35: Third party audit console (TBD) | V35: The system validation form is more detailed and precise, but it is a sampled check on the reporting system
A36: Immediate outcome | B36: 2200 | C36: ='Log frame'!F17 -> Increased household access to sustainable, affordable, and safe sanitation services.​ | D36: 2200c | E36: % of population in intervention communes with at least basic sanitation service | F36: Percentage of population in intervention communes with access to at least basic sanitation service, defined as improved and unshared facilities. "...at least basic sanitation service": Basic 1) Improved (According to the JMP classification) 2) Unshared 3) [Household level] Note: Includes basic and safely managed sanitation service. | G36: % of total # of people in the commune | H36: In service/Needs mods | I36: ="Mattson" -> Mattson | J36: Gender, age category, date, commune | K36: Household WASH survey | L36: Partner of implementation | M36: Primary (on-site survey) | N36: Launch + verification + certification | O36: Implementation monitoring console | R36: Household survey - Audit | S36: Mayors & OREPA Focal Points & HANWASH M&E Manager | T36: Annually | U36: Third party audit console (TBD) | V36: The system validation form is more detailed and precise, but it is a sampled check on the reporting system
A37: Outputs | B37: 2210 | C37: ='Log frame'!F19 -> Mobilize communities to achieve Open Defecation Free status | D37: 2210a | E37: # of people added to basic sanitation service in the intervention communes | F37: Number of people who newly gained access to basic sanitation service in the intervention communes, as a result of HANWASH interventions. "Basic sanitation service": 1) Improved (according to the JMP classification) 2) Unshared 3) [Household level] | G37: people | H37: In service/Needs mods | I37: ="Mattson" -> Mattson | J37: Gender, age category, date, commune | K37: Household WASH survey | L37: Partner of implementation | M37: Primary (on-site survey) | N37: Monthly | O37: Implementation monitoring console | R37: Household survey - Audit | S37: HANWASH M&E Manager | T37: Semi-annually | U37: Third party audit console (TBD) | V37: The system validation form is more detailed and precise, but it is a sampled check on the reporting system
A38: Outputs | B38: 2230 | C38: ='Log frame'!F23 -> Construct public latrines. | D38: 2230a | E38: # of public latrines constructed | F38: Number of public latrines constructed, improving sanitation access in communal areas. | G38: Public toilet blocks | H38: In service - Needs training | I38: HANWASH - Master | J38: Community, date, commune | K38: Public latrine form | L38: Partner of implementation | M38: Secondary | N38: Semi-annually | O38: Implementation monitoring console | R38: Household survey - Audit | S38: OREPA Focal Points & HANWASH M&E Manager | T38: Semi-annually | U38: Third party audit console (TBD) | V38: IT IS UNCLEAR HOW THIS FITS INTO HANWASH'S VISION. HOW ARE THESE TOILET BLOCKS MANAGED? IF IT IS A "CASA", THEN THEY CAN BE MANAGED AS ODF COMMUNITIES INSTEAD OF STANDALONE TOILET BLOCKS.
A39: Immediate outcome | B39: 2300 | C39: ='Log frame'!G17 -> Increased household access to hygiene services. | D39: 2300a | E39: % of population in intervention communes with at least basic hygiene service | F39: Percentage of population in intervention communes with access to at least basic hygiene service, defined as presence of a handwashing facility with soap and water on premises. "...at least basic hygiene service" (according to the JMP classification): 1) Presence of a Hanwashing facility on premises 2) Presence of soap and water Notes: Also include people with access to hygiene services higher than basic. (we don't know yet what this looks like) | G39: % of people within intervention communities | H39: In service - Needs mods | I39: ="Mattson" -> Mattson | J39: Gender, age category | K39: Household WASH survey | L39: Partner of implementation | M39: Primary (on-site survey) | N39: Launch + verification + certification | O39: Implementation monitoring console | R39: Household survey - Audit | S39: Mayors & OREPA Focal Points & HANWASH M&E Manager | T39: Semi-annually | U39: Third party audit console (TBD) | V39: The Household survey - Audit is more detailed and precise, but it is a sampled check on the reporting system
A40: Outputs | B40: 2310 | C40: ='Log frame'!G19 -> Train skilled community animators to deliver hygiene trainings and community mobilization.​ | D40: 2310a | E40: # of community animators trained | F40: Number of community animators/coaches trained to provide leadership and WASH training to people in the intervention communities. | G40: animators/coaches | H40: In service - Needs mods | I40: ="Mattson" -> Mattson | J40: Date, commune | K40: Training sessions tracking form (TBD) | L40: Partner of implementation | M40: Primary (on-site survey) | N40: Quarterly | O40: Implementation monitoring console | R40: Review of existing data | S40: Mayors & HANWASH M&E Manager | T40: Semi-annually | U40: Implementation monitoring console | V40: System validation consists of a sampled desk review of reported data
A41: Outputs | B41: 2310 | C41: Train skilled community animators to deliver hygiene trainings and community mobilization.​ | D41: 2310b | E41: # of hours of hygiene trainings and community mobilization provided by the community animators trained | F41: Cumulative number of hours of leadership and WASH training delivered by trained community animators/coaches. This indicator measures the intensity of leadership and WASH training delivered by the community animators. It is the sum of hours the community animator spends providing those trainings to people in the intervention communities. | G41: Cumulative number of hours of training | H41: Not started | I41: Mattson | J41: Date, commune, communities | K41: Training sessions tracking form | L41: Partner of implementation | M41: Secondary | N41: Monthly | O41: Implementation monitoring console | P41: Review of existing data | Q41: Third party contractor | R41: Review of existing data | S41: HANWASH M&E Manager | T41: Semi-annually | U41: Implementation monitoring console
A42: Outputs | B42: 2320 | C42: ='Log frame'!G21 -> Certify the sustained usage of hygiene services. | D42: 2320a | E42: # of people added to basic hygiene service | F42: Number of people newly gaining access to basic hygiene service in the intervention communes as a result of HANWASH and partners interventions. "Basic hygiene service": 1) Presence of a handwashing facility on premises 2) Presence of soap and water 3) [Household level] | G42: people | H42: In service - Needs mods | I42: ="Mattson" -> Mattson | J42: Date, commune | K42: ODF verification and certification Form | L42: Partner of implementation | M42: Primary (on-site survey) | N42: Monthly | O42: Implementation monitoring console | R42: Review of existing data | S42: OREPA Focal Points & HANWASH M&E Manager | T42: Semi-annually | U42: Implementation monitoring console | V42: System validation consists of a sampled desk review of reported data
A43: Immediate outcome | B43: 2400 | C43: ='Log frame'!H17 -> Increased access to sustainable, safe drinking water, sanitation, and hygiene materials in healthcare facilities, schools, and public places. | D43: 2400a | E43: % of schools with at least basic drinking water, sanitation, and hygiene services | F43: Percentage of schools in intervention communes with basic drinking water, sanitation, and hygiene services, meeting WHO/UNICEF JMP criteria for schools. '"Basic drinking water service": 1) Improved 2) Currently available "Basic sanitation service": 1) Improved 2) Usable 3) Gender separated toilets available "Basic hygiene service": 1) Presence of handwashing facilities 2) Presence of soap and water | G43: % of total number of schools in intervention communes | H43: In service - Needs training | I43: HANWASH - Master | J43: Water service level, sanitation service level, hygiene service level, date, commune | K43: School WASH form | L43: Partner of implementation | M43: Primary (on-site survey) | N43: Annually | O43: Implementation monitoring console | R43: School WASH form - Audit | S43: OREPA Focal Points & HANWASH M&E Manager | T43: Annually | U43: Third party audit console (TBD) | V43: The reporting and system validation forms are the same, just different deployments carried out by different stakeholders. Reporting: PMO. Validation: Third party contractor.
A44: Immediate outcome | B44: 2400 | C44: ='Log frame'!H17 -> Increased access to sustainable, safe drinking water, sanitation, and hygiene materials in healthcare facilities, schools, and public places. | D44: 2400b | E44: % of healthcare facilities with at least basic drinking water, sanitation, and hygiene services | F44: Percentage of healthcare facilities in intervention areas with basic drinking water, sanitation, and hygiene services, meeting WHO/UNICEF JMP criteria for healthcare facilities. "Basic drinking water service": 1) Improved 2) On premises 3) Currently available "Basic sanitation service": 1) Improved 2) Usable 3) Dedicated for staff 4) Sex-separated with menstrual hygiene facilities 5) Accessible for users with limited mobility "Basic hygiene service": ...At points of care 1) Facilities present 2) Soap and water or alcohol based hand rub present ...At toilets 1) Within 5 m of toilets 2) Facilities present 3) Soap and water present | G44: % of total number of healthcare facilities in intervention communes | H44: In service - Needs training | I44: HANWASH - Master | J44: Water service level, sanitation service level, hygiene service level, date, commune | K44: Healthcare facility WASH form | L44: Partner of implementation | M44: Primary (on-site survey) | N44: Annually | O44: Implementation monitoring console | R44: Healthcare facility WASH form - Audit | S44: OREPA Focal Points & HANWASH M&E Manager | T44: Annually | U44: Third party audit console (TBD) | V44: The reporting and system validation forms are the same, just different deployments carried out by different stakeholders. Reporting: PMO. Validation: Third party contractor.
A45: Outputs | B45: 2410 | C45: ='Log frame'!H19 -> Construct or rehabilitate water supply for healthcare facilities and schools. | D45: 2410a | E45: # of schools added with basic drinking water services | F45: Number of schools newly provided with basic drinking water services in intervention communes, as a result of HANWASH and partners' interventions, meeting WHO/UNICEF JMP criteria for schools. "Basic drinking water service": 1) Improved 2) Currently available 3) potable | G45: schools | H45: In service - Needs training | I45: HANWASH - Master | J45: Water service level, date, commune | K45: School WASH form | L45: Partner of implementation | M45: Primary (on-site survey) | N45: Semi-annually | O45: Implementation monitoring console | R45: School WASH form - Audit | S45: OREPA Focal Points & HANWASH M&E Manager | T45: Annually | U45: Third party audit console (TBD) | V45: The reporting and system validation forms are the same, just different deployments carried out by different stakeholders. Reporting: PMO. Validation: Third party contractor.
A46: Outputs | B46: 2410 | C46: ='Log frame'!H19 -> Construct or rehabilitate water supply for healthcare facilities and schools. | D46: 2410b | E46: # of healthcare facilities added with basic drinking water services | F46: Number of healthcare facilities newly provided with basic drinking water services in intervention communes, as a result of HANWASH and partners' interventions, meeting WHO/UNICEF JMP criteria for healthcare facilities. "Basic drinking water service": 1) Improved 2) On premises 3) Currently available 4) Potable | G46: healthcare facilities | H46: In service - Needs training | I46: HANWASH - Master | J46: Water service level, date, commune | K46: Healthcare facility WASH form | L46: Partner of implementation | M46: Primary (on-site survey) | N46: Semi-annually | O46: Implementation monitoring console | R46: Healthcare facility WASH form - Audit | S46: OREPA Focal Points & HANWASH M&E Manager | T46: Annually | U46: Third party audit console (TBD) | V46: The reporting and system validation forms are the same, just different deployments carried out by different stakeholders. Reporting: PMO. Validation: Third party contractor.
A47: Outputs | B47: 2420 | C47: ='Log frame'!H21 -> Construct communal, healthcare facility, and school latrines. | D47: 2420a | E47: # of schools added with basic sanitation services | F47: Number of schools newly provided with basic sanitation services in the intervention communes, as a result of HANWASH and partners' interventions, meeting WHO/UNICEF JMP criteria for schools. "Basic sanitation service": 1) Improved 2) Usable 3) Gender separated toilets available | G47: schools | H47: In service - Needs training | I47: HANWASH - Master | J47: Sanitation service level, date, commune | K47: School WASH form | L47: Partner of implementation | M47: Primary (on-site survey) | N47: Semi-annually | O47: Implementation monitoring console | R47: School WASH form - Audit | S47: OREPA Focal Points & HANWASH M&E Manager | T47: Annually | U47: Third party audit console (TBD) | V47: The reporting and system validation forms are the same, just different deployments carried out by different stakeholders. Reporting: PMO. Validation: Third party contractor.
A48: Outputs | B48: 2420 | C48: ='Log frame'!H21 -> Construct communal, healthcare facility, and school latrines. | D48: 2420b | E48: # of healthcare facilities added with basic sanitation services | F48: Number of healthcare facilities newly provided with basic sanitation services in the intervention communes, as a result of HANWASH and partners' interventions, meeting WHO/UNICEF JMP criteria for healthcare facilities. "Basic sanitation services": 1) Improved 2) Usable 3) Separated for staff and patients 4) Gender separated with menstrual hygiene facilities 5) Accessible for users with limited mobility | G48: healthcare facilities | H48: In service - Needs training | I48: HANWASH - Master | J48: Sanitation service level, date, commune | K48: Healthcare facility WASH form | L48: Partner of implementation | M48: Primary (on-site survey) | N48: Semi-annually | O48: Implementation monitoring console | R48: Healthcare facility WASH form - Audit | S48: OREPA Focal Points & HANWASH M&E Manager | T48: Annually | U48: Third party audit console (TBD) | V48: The reporting and system validation forms are the same, just different deployments carried out by different stakeholders. Reporting: PMO. Validation: Third party contractor.
A49: Outputs | B49: 2430 | C49: ='Log frame'!H23 -> Work with (local authorities, civil society) to ensure access to soap or alcohol-based handrub at schools and healthcare facilities. | D49: 2430a | E49: # of schools added with basic hygiene | F49: Number of schools newly provided with basic hygiene services in the intervention communes, as a result of HANWASH and partners' interventions, meeting WHO/UNICEF JMP criteria for schools. "Basic hygiene": 1) Presence of handwashing facilities 2) Presence of soap and water | G49: schools | H49: In service - Needs training | I49: HANWASH - Master | J49: Hygiene servicec level, date, commune | K49: School WASH form | L49: Partner of implementation | M49: Primary (on-site survey) | N49: Semi-annually | O49: Implementation monitoring console | R49: School WASH form - Audit | S49: OREPA Focal Points & HANWASH M&E Manager | T49: Annually | U49: Third party audit console (TBD) | V49: The reporting and system validation forms are the same, just different deployments carried out by different stakeholders. Reporting: PMO. Validation: Third party contractor.
A50: Outputs | B50: 2430 | C50: ='Log frame'!H23 -> Work with (local authorities, civil society) to ensure access to soap or alcohol-based handrub at schools and healthcare facilities. | D50: 2430b | E50: # of healthcare facilities added with basic hygiene | F50: Number of healthcare facilities newly provided with basic hygiene services in the intervention communes, as a result of HANWASH and partners' interventions, meeting WHO/UNICEF JMP criteria for healthcare facilities. "Basic hygiene": ...At points of care 1) Facilities present 2) Soap and water or alcohol based hand rub present ...At toilets 1) Within 5 m of toilets 2) Facilities present 3) Soap and water present | G50: healthcare facilities | H50: In service - Needs training | I50: HANWASH - Master | J50: Hygiene service level, date, commune | K50: Healthcare facility WASH form | L50: Partner of implementation | M50: Primary (on-site survey) | N50: Semi-annually | O50: Implementation monitoring console | R50: Healthcare facility WASH form - Audit | S50: OREPA Focal Points & HANWASH M&E Manager | T50: Annually | U50: Third party audit console (TBD) | V50: The reporting and system validation forms are the same, just different deployments carried out by different stakeholders. Reporting: PMO. Validation: Third party contractor.
A51: Intermediate outcome | B51: 3000 | C51: ='Log frame'!I15 -> Expanded reach and resources leveraged through collective action with other national and international actors.​ | D51: - | E51: - | F51: - | G51: - | H51: - | I51: ="Mattson" -> Mattson | J51: - | K51: - | L51: - | N51: - | O51: - | P51: - | Q51: - | R51: - | S51: - | T51: - | U51: - | V51: This objective is split into its component objectives and measured via their indicators
A52: Immediate outcome | B52: 3100 | C52: ='Log frame'!I17 -> Increased government and non-government funding in alignment with HANWASH Core Values. | D52: 3100a | E52: Cumulative amount of money committed in alignment with HANWASH Core Values, supported by an MOU signed with HANWASH | F52: Cumulative amount of money (in USD) committed to projects aligned with HANWASH Core Values: local leadership, collaboration, systematic approach, impact, and commitment. Aligned with HANWASH Core Values: **LOCALLY LED** We strengthen community participation in governance of WASH infrastructure and services. **COLLABORATIVE** Volunteers, government authorities, and partners are meaningfully engaged, and a MOU is signed among the parties. ### **SYSTEMATIC** We will be thoughtful and consistent in planning, doing, and improving our work.** **IMPACTFUL** Sustainability is a key metric of our success. **COMMITTED** We will not stop until the job is done. | G52: USD | H52: In service | I52: ="Mattson" -> Mattson | J52: Actor, project type date, commune | K52: HANWASH financial records & MOU signed with partners | L52: HANWASH CFO | M52: Secondary | N52: Annually | O52: Project monitoring console | R52: Review of existing data | S52: HANWASH Country Director | T52: Annually | U52: Project monitoring console | V52: Since this indicator is completed by the HANWASH M&E Manager, HANWASH should review the results with DINEPA as a check on the reporting system
A53: Immediate outcome | B53: 3100 | C53: ='Log frame'!I17 -> Increased government and non-government funding in alignment with HANWASH Core Values. | D53: 3100b | E53: % of committed money which has been spent (cumulative), supported by an MOU signed with HANWASH | F53: Percentage of committed funds that have been spent, calculated as (Cumulative_amount_spent / Cumulative_amount_committed) * 100. | G53: % of amount committeed | H53: In service - Needs training | I53: Mattson | J53: Commune, project, date | K53: HANWASH financial records & MOU signed with partners | L53: HANWASH CFO | M53: Secondary | N53: Annually | O53: Project monitoring console | R53: Review of existing data | S53: HANWASH Country Director | T53: Annually | U53: Third party audit console (TBD) | V53: System validation consists of a sampled desk review of reported data
A54: Outputs | B54: 3110 | C54: ='Log frame'!I19 -> Mobilize and coordinate funding from government and non-government sources in HANWASH program areas in alignment with HANWASH Core Values. | D54: 3110a | E54: Amount of money spent by external actors within HANWASH project areas, supported by an MOU signed with HANWASH The term "project areas" refers to the geographic locations or regions where a specific project is being implemented or where project activities are taking place. | F54: Cumulative amount of money (in USD) spent by external (non-rotarian) actors within HANWASH project areas, aligned with HANWASH Core Values. | G54: USD | H54: In service | I54: ="Mattson" -> Mattson | J54: Actor, date, commune | K54: HANWASH financial records & MOU signed with partners | L54: HANWASH CFO | M54: Secondary | N54: Annually | O54: Project monitoring console | R54: Review of existing data | S54: HANWASH Country Director | T54: Annually | U54: Project monitoring console | V54: Since this indicator is completed by the HANWASH M&E Manager, HANWASH should review the results with DINEPA as a check on the reporting system
A55: Outputs | B55: 3120 | C55: ='Log frame'!I21 -> Mobilize and influence funding from government and non-government sources beyond HANWASH program areas in alignment with HANWASH Core Values. | D55: 3120a | E55: Amount of money spent by external actors beyond project areas in alignment with HANWASH Core Values, supported by an MOU signed with HANWASH The term "project areas" refers to the geographic locations or regions where a specific project is being implemented or where project activities are taking place. | F55: Cumulative amount of money (in USD) spent by external (non-rotarian) actors beyond HANWASH project areas but still within the WASH sector and aligned with HANWASH Core Values, extending impact. | G55: USD | H55: In service | I55: HANWASH - Master | J55: Actor, date, commune | K55: HANWASH financial records & MOU signed with partners | L55: HANWASH CFO | M55: Secondary | N55: Annually | O55: Project monitoring console | R55: Review of existing data | S55: HANWASH Country Director | T55: Annually | U55: Project monitoring console | V55: Since this indicator is completed by the HANWASH M&E Manager, HANWASH should review the results with DINEPA as a check on the reporting system
A56: Immediate outcome | B56: 3200 | C56: ='Log frame'!J17 -> Increased capacity of DINEPA to regulate the sector and OREPA to oversee and support implementation. | D56: 3200a | E56: % of implementing partners in HANWASH program areas who have signed the DINEPA Accord Cadre | F56: Percentage of implementing partners in HANWASH program areas who have signed the DINEPA Accord Cadre, ensuring alignment with national standards. (Number of IPs who have signed the Accord Cadre / Total number of IPs in HANWASH program areas) x 100 | G56: % of implementing partners in HANWASH program areas | H56: In service - Needs mods | I56: ="Mattson" -> Mattson | J56: Post/position, commune, department, date | K56: SIEPA Accord Cadre | L56: HANWASH Country Director | M56: Secondary | N56: Annually | O56: - | P56: - | Q56: - | R56: - | S56: OREPA Focal Points | T56: Annually | U56: - | V56: Since this information is contained in SIEPA, the HANWASH M&E Manager should work with ONEPA to aquire the data. Validation
A57: Outputs | B57: 3220 | C57: ='Log frame'!J21 -> Provide technical assistance and training to DINEPA and the OREPAs. | D57: 3220a | E57: # of technical trainings provided for DINEPA priority areas | F57: Number of technical trainings provided for DINEPA priority areas, focusing on key topics such as unified national tariff methodology and ODF certification. Priorities areas for 2023-24: Unified national tariff methodology & ODF certification. Priorities areas for 2024-2025: ? Priorities areas for 2025-2026: ? | G57: trainings | H57: In service - Needs training | I57: ="Mattson" -> Mattson | J57: Date, commune | K57: Implementation event tracking form | L57: Partner of implementation | M57: Secondary | N57: Quarterly | O57: Implementation monitoring console | R57: Review of existing data | S57: HANWASH M&E Manager | T57: Semi-annually | U57: Implementation monitoring console | V57: System validation consists of a sampled desk review of reported data

Sheet Log frame
A1: Organization: HANWASH | E1: Legend
A2: Document: Master logic model | E2: Active objectives - Included in current action plan
A3: Objective: Define the objectives of the program. | E3: Inactive objectives - Not included in current action plan
A4: Scope: HANWASH programs
A5: Reference link: Click here
A6: Version number: 2.4
A7: Version date: Sept. 11, 2023
A8: Notes: The lower level objectives should cause the higher level objectives.
A10: Objectives
A11: Type | B11: Description
A12: Ultimate outcome | B12: 1
B13: Increased access to safe, sustainable and affordable water, sanitation and hygiene (WASH) services in Haiti​.
A14: Intermediate outcomes | B14: 1000 | E14: 2000 | I14: 3000
B15: Strengthened demand for and management of WASH services in communes. | E15: Enhanced household access to and use of sustainable, affordable, and safe water, sanitation and hygiene services.​ | I15: Expanded reach and resources leveraged through collective action with other national and international actors.​
A16: Immediate outcomes | B16: 1100 | C16: 1200 | D16: 1300 | E16: 2100 | F16: 2200 | G16: 2300 | H16: 2400 | I16: 3100 | J16: 3200
B17: Increased civil society engagement in decision making and implementation of WASH services. | C17: Improved commune WASH planning and coordination by local authorities.​ | D17: Improved accountability of service providers to users of WASH services.​ | E17: Increased household access to sustainable, affordable, and safe drinking water services.​ | F17: Increased household access to sustainable, affordable, and safe sanitation services.​ | G17: Increased household access to hygiene services. | H17: Increased access to sustainable, safe drinking water, sanitation, and hygiene materials in healthcare facilities, schools, and public places. | I17: Increased government and non-government funding in alignment with HANWASH Core Values. | J17: Increased capacity of DINEPA to regulate the sector and OREPA to oversee and support implementation.
A18: Outputs | B18: 1110 | C18: 1210 | D18: ​1310 | E18: 2110 | F18: 2210 | G18: 2310 | H18: 2410 | I18: 3110 | J18: 3210
B19: Support civil society engagement in the WASH sector.​ | C19: Create or improve commune action plans that focus on water, sanitation and hygiene, and water resource management.​ | D19: Monitor WASH service performance and satisfaction. | E19: Develop community managed water points. | F19: Mobilize communities to achieve Open Defecation Free status | G19: Train skilled community animators to deliver hygiene trainings and community mobilization.​ | H19: Construct or rehabilitate water supply for healthcare facilities and schools. | I19: Mobilize and coordinate funding from government and non-government sources in HANWASH program areas in alignment with HANWASH Core Values. | J19: Conduct leadership training of DINEPA and OREPA personnel.
B20: 1120 | C20: 1220 | D20: 1320 | E20: 2120 | F20: 2220 | G20: 2320 | H20: 2420 | I20: 3120 | J20: 3220
B21: Train HANWASH Ambassadors & Coordinators and their committees throughout the Caribbean.​ | C21: Facilitate coordination meetings between commune WASH stakeholders. | D21: Review service provider performance with stakeholders. | E21: Rehabilitate and expand professionally operated piped water systems. | F21: Certify the sustained usage of sanitation services. | G21: Certify the sustained usage of hygiene services. | H21: Construct communal, healthcare facility, and school latrines. | I21: Mobilize and influence funding from government and non-government sources beyond HANWASH program areas in alignment with HANWASH Core Values. | J21: Provide technical assistance and training to DINEPA and the OREPAs.
F22: 2230 | H22: 2430
F23: Construct public latrines. | H23: Work with (local authorities, civil society) to ensure access to soap or alcohol-based handrub at schools and healthcare facilities.

Sheet Indicator framework-Initial
A1: Organization: HANWASH | E1: Legend
A2: Document: Indicator framework | E2: TBD' To be determined | F2: ="'-' Not applicable" -> '-' Not applicable
A3: Objective: Define indicators to measure progress towards each objective.
A4: Scope: HANWASH programs | E4: Objective types | F4: Description
A5: Reference link: This document | E5: Ultimate outcome | F5: The highest level objective of HANWASH. These are not directly measureable by SMART indicators, but measured indirectly via indicators of their component Intermediate Outcomes.
A6: Version number: 2.41 | E6: Intermediate outcome | F6: The component objectives of the HANWASH ultimate outcome. These are not directly measureable by SMART indicators, but measured indirectly via indicators of their component Intermediate Outcomes.
A7: Version date: March 21, 2024 | E7: Immediate outcome | F7: The higher level objective that HANWASH seeks to achieve, which are able to be measured directly by SMART indicators. Indicators measuring these outcomes are typically expressed as a percent, which are harder to measure, but builds the context into the measure.
A8: Notes: SMART indicators are indicators which are specific, measureable, achievable, relevant, and time-bound. | E8: Output | F8: The lower level objective that HANWASH seeks to achieve. Indicators measuring these outcomes are typically expressed as a number, which is easier to measure, but also easier to take out of context.
E9: Kept in revised version
E10: Replaced in revised version
E11: Removed in revised version
A13: Objective | D13: Indicator | K13: Reporting system | P13: Commune validation | R13: Reporting system validation | V13: Notes
A14: Type | B14: Code | C14: Description | D14: Code_index | E14: Description | F14: Definitions | G14: Units | H14: Status | I14: Program | J14: (Dis)Aggregation | K14: Source | L14: Enumerator | M14: Type of data collection | N14: Frequency | O14: Visualization | P14: Data source | Q14: Data collection | R14: Source | S14: Validator | T14: Frequency | U14: Visualization
A15: Ultimate outcome | B15: 1 | C15: ='Log frame'!B13 -> Increased access to safe, sustainable and affordable water, sanitation and hygiene (WASH) services in Haiti​. | D15: - | E15: - | F15: - | G15: - | H15: - | I15: ="Mattson" -> Mattson | J15: - | K15: - | L15: - | N15: - | O15: - | P15: - | Q15: - | R15: - | S15: - | T15: - | U15: - | V15: This objective is split into its component objectives and measured via their indicators
A16: Intermediate outcome | B16: 1000 | C16: ='Log frame'!B15 -> Strengthened demand for and management of WASH services in communes. | D16: - | E16: - | F16: - | G16: - | H16: - | I16: ="Mattson" -> Mattson | J16: - | K16: - | L16: - | N16: - | O16: - | P16: - | Q16: - | R16: - | S16: - | T16: - | U16: - | V16: This objective is split into its component objectives and measured via their indicators
A17: Immediate outcome | B17: 1100 | C17: ='Log frame'!B17 -> Increased civil society engagement in decision making and implementation of WASH services. | D17: 1100a | E17: % of commune WASH events with Rotarian participation | F17: Percentage of commune-level WASH events that have active Rotarian participation, measured as a proportion of total reported events. | G17: % of total commune levelWASH events reported | H17: In service - Needs training | I17: ="Mattson" -> Mattson | J17: Event type, participant group, date, commune | K17: Implementation event tracking form | L17: Rotary ambassadors | N17: After every implementation event | O17: Implementation monitoring console | R17: Review of existing data | S17: HANWASH M&E officer | T17: Quarterly | U17: Implementation monitoring console | V17: System validation consists of an exhaustive desk review of both the PMO and Rotarians forms.
A18: Immediate outcome | B18: 1100 | C18: Increased civil society engagement in decision making and implementation of WASH services. | D18: 1100b | E18: % of commune WASH events led by trained HANWASH Ambassadors and Coordinators to communicate WASH messages and advocate for HANWASH goal | F18: Percentage of commune-level WASH events led by trained HANWASH Ambassadors and Coordinators to communicate WASH messages and advocate for HANWASH mission and goal, measured as a proportion of total reported WASH events. "…led by Rotarians…" means the WASH events whose initiative have been taken by Rotarians. | G18: % of commune level WASH events reported | H18: Not started | I18: Mattson | J18: Event type, participant group, date, commune | K18: Implementation event tracking form | L18: Rotary ambassadors | N18: After every implementation event | O18: Implementation monitoring console | P18: Review of existing data | Q18: HANWASH M&E officer | R18: Review of existing data | S18: HANWASH M&E officer | T18: Quarterly | U18: Implementation monitoring console
A19: Outputs | B19: 1110 | C19: Support civil society engagement in the WASH sector.​ | D19: 1110a | E19: # of volunteer hours per month spent by Rotarians in WASH events | F19: Total number of hours contributed by Rotarians each month through volunteer activities related to water, sanitation, and hygiene (WASH) events for the HANWASH initiative. WASH event can be defined as: "A structured activity organized or supported by HANWASH or its partners that directly contributes to improving water, sanitation, or hygiene outcomes in Haiti. This includes project design and implementation, community mobilization, hygiene promotion, technical assessments, training sessions, or advocacy efforts involving Rotarian volunteers." Notes: *"Structured activity" implies a planned and time-bound engagement. *The activity should be directly relevant to WASH outcomes. *On-site and remote support is included (e.g., virtual trainings, planning sessions, etc.). | G19: volunteer hours / month | H19: In service - Needs training | I19: ="Mattson" -> Mattson | J19: Event type, participant group, date, commune | K19: Implementation event tracking form | L19: Rotary ambassadors | N19: After every implementation event | O19: Implementation monitoring console | R19: Review of existing data | S19: HANWASH M&E officer | T19: Quarterly | U19: Implementation monitoring console | V19: System validation consists of an exhaustive desk review of both the PMO and Rotarians forms.
A20: Outputs | B20: 1110 | C20: Support civil society engagement in the WASH sector.​ | D20: 1110b | E20: Number of people reached by the HANWASH Ambassadors, Coordinators and Rotarians in general in the Commune WASH events and advocacy efforts led by them | F20: Total number of individuals reached through WASH events and advocacy efforts led by HANWASH Ambassadors, Coordinators, and other Rotarians from and outside of Haiti. | G20: people | H20: In service - Needs training | I20: Mattson | J20: Event type, participant group, date, commune | K20: Implementation event tracking form | L20: Rotary ambassadors | N20: After every implementation event | O20: Implementation monitoring console | P20: Review of existing data | Q20: HANWASH M&E officer | R20: Quarterly | S20: HANWASH M&E officer | T20: Quarterly
A21: Outputs | B21: 1120 | C21: ='Log frame'!B21 -> Train HANWASH Ambassadors & Coordinators and their committees throughout the Caribbean.​ | D21: 1120a | E21: # of ambassadors who have completed training | F21: Total number of HANWASH Ambassadors who have successfully completed the required training program. | G21: people | H21: In service - Needs training | I21: ="Mattson" -> Mattson | J21: Training type, date, commune | K21: Implementation event tracking form | L21: PMO | N21: After every training event | O21: Implementation monitoring console | R21: Review of existing data | S21: HANWASH M&E officer | T21: Quarterly | U21: Implementation monitoring console | V21: System validation consists of a sampled desk review of reported data
A22: Outputs | B22: 1120 | C22: ='Log frame'!B21 -> Train HANWASH Ambassadors & Coordinators and their committees throughout the Caribbean.​ | D22: 1120b | E22: # of coordinators who have completed training | F22: Total number of HANWASH Coordinators who have successfully completed the required training program. | G22: people | H22: In service - Needs training | I22: ="Mattson" -> Mattson | J22: Training type, date, commune | K22: Implementation event tracking form | L22: PMO | N22: After every training event | O22: Implementation monitoring console | R22: Review of existing data | S22: HANWASH M&E officer | T22: Quarterly | U22: Implementation monitoring console | V22: System validation consists of a sampled desk review of reported data
A23: Outputs | B23: 1120 | C23: Train HANWASH Ambassadors & Coordinators and their committees throughout the Caribbean.​ | D23: 1120c | E23: # of training materials created in alignment with HANWASH three pillars and core values | F23: Total number of training materials developed that align with HANWASH's three pillars and core values. | G23: Training materials | H23: Not started | I23: Mattson | J23: Training type | K23: Implementation event tracking form | L23: PMO | N23: Annually | O23: Implementation monitoring console | P23: Review of existing data | Q23: HANWASH M&E officer | R23: Review of existing data | S23: HANWASH M&E officer | T23: Quarterly | U23: Implementation monitoring console
A24: Outputs | B24: 1120 | C24: Train HANWASH Ambassadors & Coordinators and their committees throughout the Caribbean.​ | D24: 1120d | E24: # of hours of training received by the HANWASH Ambassadors & Coordinators and their committees throughout the Caribbean | F24: Cumulative number of training hours received by HANWASH Ambassadors, Coordinators, and their committees throughout the Caribbean region. | G24: Hours of training | H24: Not started | I24: Mattson | J24: Training type | K24: Implementation event tracking form | L24: PMO | N24: Quarterly | O24: Implementation monitoring console | P24: Review of existing data | Q24: Implementation monitoring console | R24: Review of existing data | S24: HANWASH M&E officer | T24: Quarterly | U24: Implementation monitoring console
A25: Immediate outcome | B25: 1200 | C25: ='Log frame'!C17 -> Improved commune WASH planning and coordination by local authorities.​ | D25: 1200a | E25: % of approved interventions implemented in alignment with Commune Action Plans | F25: Percentage of the interventions that have received formal approval/assignment from the Mayors offices through a demand letter or other written documents which have been implemented or are in-process by HANWASH or its partners. The approved interventions are subsets of the commune action plans which are assigned to HANWASH or its partners by the Mayor's Offices. | G25: % of implemented activities | H25: In service - Needs mods | I25: ="Mattson" -> Mattson | J25: Date, commune | K25: HANWASH project monitoring | L25: PMO | N25: Annually | O25: Project monitoring console | P25: Commune action plan | Q25: Commune WASH committee | R25: Review of existing data | S25: HANWASH M&E officer | T25: Quarterly | U25: Project monitoring console | V25: It's critical that "Activities" planned by HANWASH correspond to those in the commune action plan in the system.
A26: Outputs | B26: 1210 | C26: ='Log frame'!C19 -> Create or improve commune action plans that focus on water, sanitation and hygiene, and water resource management.​ | D26: 1210a | E26: # of communes with action plans that explicitly include each W,S,H,WRM aspect (water, sanitation, hygiene, water resources management) | F26: Number of communes with comprehensive action plans that explicitly address all four WASH aspects: Water, Sanitation, Hygiene, and Water Resources Management. | G26: communes | H26: In service - Needs mods | I26: ="Mattson" -> Mattson | J26: Date, commune | K26: HANWASH project monitoring | L26: PMO | N26: Annually | O26: Project monitoring console | R26: Review of existing data | S26: HANWASH M&E officer | T26: Quarterly | U26: Project monitoring console | V26: System validation consists of an exhaustive desk review of reported data
A27: Outputs | B27: 1220 | C27: ='Log frame'!C21 -> Facilitate coordination meetings between commune WASH stakeholders. | D27: 1220a | E27: # of WASH planning and coordination events with DINEPA and municipal officials | F27: Number of WASH planning and coordination events conducted with DINEPA and municipal officials per month, fostering collaboration and alignment. | G27: events/month | H27: In service - Needs training | I27: ="Mattson" -> Mattson | J27: Event type, participant group, date, commune | K27: Implementation event tracking form | L27: PMO | N27: After every joint event | O27: Implementation monitoring console | R27: Review of existing data | S27: HANWASH M&E officer | T27: Quarterly | U27: Implementation monitoring console | V27: System validation consists of a sampled desk review of reported data
A28: Immediate outcome | B28: 1300 | C28: ='Log frame'!D17 -> Improved accountability of service providers to users of WASH services.​ | D28: 1300a | E28: % of service providers under HANWASH initiative monitored according to national guidelines | F28: A service provider is defined as the management structure in charge of a water system (“SAEP”) or a community-managed well (“CPE”). This indicator measures the % of service providers regularly (i.e. monthly) submitting reports to DINEPA and local authorities, according to the DINEPA's requirements in terms of indicators to be captured and data to be shared. | G28: % of the total number of service providers which received the HANWASH intervention in the target communes | H28: In service - Needs mods | I28: Mattson | J28: Water point/system, date, commune | K28: Water point survey and SAEP monthly report | L28: PMO | N28: Water point: Annually Water system: Monthly" | O28: Implementation monitoring console | R28: Water point survey - Audit | S28: Third party contractor | T28: Every two years | U28: Third party audit console (TBD) | V28: The reporting and system validation forms are the same, just different deployments carried out by different stakeholders. Reporting: PMO. Validation: Third party contractor.
A29: Immediate outcome | B29: 1300 | C29: ='Log frame'!D17 -> Improved accountability of service providers to users of WASH services.​ | D29: 1300b | E29: % of intervention service providers with accountability structures in place | F29: Percentage of intervention service providers that have established accountability structures, promoting transparency and community engagement. "Accountability structures in place", means: 1) CPE or Operator meets regularly 2) CPE or Operator meets with community regularly 3) CPE or Operator signed bylaws with OREPA and apply them 4) Water usage fees are collected on a monthly basis from the subscribers 5) Records are available; 6) Reports are submitted to OREPA and the local authorities on a monthly basis 7) Water treatment is done regularly, in alignment with OREPA's requirements 8) Water potability test is done at the water points or the water system regularly, in alignment with OREPA's requirements (at least once every quarter for the community water points) 9) A mechanism is in place to collect and resolve customers complaints | G29: % of intervention water points | H29: In service - Needs mods | I29: ="Mattson" -> Mattson | J29: Water point, date, commune | K29: Water point survey | L29: PMO | N29: On completion + annually | O29: Implementation monitoring console | P29: Water point survey | R29: Water point survey - Audit | S29: Third party contractor | T29: Every two years | U29: Third party audit console (TBD) | V29: The reporting and system validation forms are the same, just different deployments carried out by different stakeholders. Reporting: PMO. Validation: Third party contractor.
A30: Immediate outcome | B30: 1300 | C30: Improved accountability of service providers to users of WASH services.​ | D30: 1300c | E30: % of users being satisfied with the quality, affordability and reliability of the WASH services provided | F30: This indicator measures the proportion of the water customers from the intervention communes which are satisfied with the quality, affordability and reliability of the WASH services provided | G30: % of households connected to the water systems | H30: Not started | I30: Mattson | J30: Water point, commune | K30: Household survey | L30: PMO | N30: On completion + annually | O30: Implementation monitoring console | P30: Water point survey - Audit | Q30: Third party contractor | R30: Review of existing data | S30: HANWASH M&E Officer | T30: Annually | U30: Implementation monitoring console
A31: Outputs | B31: 1310 | C31: ='Log frame'!D19 -> Monitor WASH service performance and satisfaction. | D31: 1310a | E31: # of intervention water systems regularly reporting data | F31: Number of intervention water systems that consistently report data on a regular basis, in alignment with OREPA's requirements, demonstrating operational transparency. "Regularly reporting data": 1) Submitted their monthly report | G31: water systems | H31: In service - Needs training | I31: ="Mattson" -> Mattson | J31: Date, commune | K31: Implementation event tracking form | L31: PMO | N31: After every training event | O31: Implementation monitoring console | R31: Review of existing data | S31: HANWASH M&E officer | T31: Quarterly | U31: Implementation monitoring console | V31: System validation consists of a sampled desk review of reported data
A32: Outputs | B32: 1310 | C32: Monitor WASH service performance and satisfaction. | D32: 1310b | E32: % of customer complaints resolved during the month | F32: Percentage of customer complaints resolved during the month, calculated as (number of resolved complaints during the month/ total number of complaints received during the month) * 100. | G32: % of total number of complaints received during the month | H32: In service - Needs training | I32: Mattson | J32: Water system, date, commune | K32: SAEP monthly report | L32: Water service provider | N32: Monthly | O32: Implementation monitoring console | P32: Review of existing data | Q32: HANWASH M&E officer | R32: Quarterly | S32: Implementation monitoring console | T32: System validation consists of a sampled desk review of reported data
A33: Outputs | B33: 1310 | C33: ='Log frame'!D19 -> Monitor WASH service performance and satisfaction. | D33: 1310c | E33: Average response time to resolve customer complaints | F33: This indicator measures how long it takes on average for the service providers to resolve customer complaints. This is the Average number of days taken to resolve customer complaints, indicating responsiveness and service quality. | G33: Days | H33: Not started | I33: ="Mattson" -> Mattson | J33: Water system, date, commune | K33: SAEP monthly report, Implementation Event tracking, Service Provider Monitoring form | L33: Water service provider | N33: Monthly | O33: Implementation monitoring console | R33: Review of existing data | S33: HANWASH M&E officer | T33: Quarterly | U33: Implementation monitoring console | V33: System validation consists of a sampled desk review of reported data
A34: Outputs | B34: 1320 | C34: ='Log frame'!D21 -> Review service provider performance with stakeholders. | D34: 1320a | E34: # of communes which have held an annual service provider review with key stakeholders in the last year | F34: This indicator measures the number of communes within the program area that have conducted at least one formal, documented annual review meeting in the past 12 months to assess the performance of water and sanitation service providers. The review must involve key stakeholders, including the Commune Committee (CASEC/ASEC or local authorities), users (e.g., representatives of community water users), service providers (e.g., water system operators), and implementing partners (e.g., NGOs, donors, or government agencies involved in WASH service delivery). Key Criteria for Counting a Commune as Having Met the Indicator: 1) A service provider performance review meeting was held within the last 12 months. 2) The meeting was convened or co-organized by the commune authority or another recognized coordinating body. 3) Representatives from all four stakeholder groups (Commune Committee, users, service providers, implementing partners) were invited and at least three attended. 4) The meeting included a structured agenda covering topics such as service quality, financial performance, user satisfaction, and challenges. 5) Meeting minutes or a summary report was produced and made available to participants. | G34: communes | H34: In service - Needs mods | I34: ="Mattson" -> Mattson | J34: Water system, date, commune | K34: SAEP monthly report | L34: Water service provider | N34: Monthly | O34: Implementation monitoring console | R34: - | S34: HANWASH M&E officer | T34: Quarterly | U34: Implementation monitoring console | V34: System validation consists of a sampled desk review of reported data
A35: Intermediate outcome | B35: 2000 | C35: ='Log frame'!E15 -> Enhanced household access to and use of sustainable, affordable, and safe water, sanitation and hygiene services.​ | D35: - | E35: - | F35: - | G35: - | H35: - | I35: ="Mattson" -> Mattson | J35: - | K35: - | L35: - | N35: - | O35: - | P35: - | Q35: - | R35: - | S35: - | T35: - | U35: - | V35: This objective is split into its component objectives and measured via their indicators
A36: Immediate outcome | B36: 2100 | C36: ='Log frame'!E17 -> Increased household access to sustainable, affordable, and safe drinking water services.​ | D36: 2100a | E36: % of intervention water points which are functioning and potable | F36: Percentage of intervention water points that are both functioning and providing potable water, ensuring access to safe drinking water. "Functioning": 1a) Functional: Water point is in good working condition and regularly provides water according the specifications in the original design. OR 1b) Partially functional but in need of repair: Water point provides water on a regular basis (possibly in a reduced capacity) but repairs are needed due to some maintenance issue or change in conditions at the site. Potable: 2) Free from E. Coli and priority contaminants | G36: % of intervention water points | H36: In service - Needs training | I36: ="Mattson" -> Mattson | J36: Date, commune | K36: Water point survey | L36: PMO | N36: On completion + annually | O36: Implementation monitoring console | R36: Household survey - Audit | S36: Third party contractor | T36: Every two years | U36: Third party audit console (TBD) | V36: The system validation form is more detailed and precise, but it is a sampled check on the reporting system
A37: Immediate outcome | B37: 2100 | C37: ='Log frame'!E17 -> Increased household access to sustainable, affordable, and safe drinking water services.​ | D37: 2100b | E37: % of population in intervention communes with at least basic drinking water service | F37: Percentage of population in intervention communes with access to at least basic drinking water service, defined as an improved water source within 30 minutes round trip. "...at least basic drinking water service": 1) Improved water source (according to the JMP classification) 2) Within 30 min round trip Note: This also includes basic and safely managed water service. | G37: % of people in the commune | H37: In service - Needs training | I37: ="Mattson" -> Mattson | J37: Community, date, commune, improved water source, within 30 min round trip | K37: Household WASH survey | L37: PMO | N37: On completion + annually | O37: Implementation monitoring console | R37: Household survey - Audit | S37: Third party contractor | T37: Every two years | U37: Third party audit console (TBD) | V37: The system validation form is more detailed and precise, but it is a sampled check on the reporting system
A38: Immediate outcome | B38: 2100 | C38: ='Log frame'!E17 -> Increased household access to sustainable, affordable, and safe drinking water services.​ | D38: 2100c | E38: % of population in intervention communes with safely managed drinking water service | F38: Percentage of population in intervention communes with access to safely managed drinking water service, defined as an improved water source accessible on premises, available when needed, and free from contamination. "Safely managed drinking water service": 1) Improved water source (according to the JMP classification) 2) Accessible on premises 3) Available when needed 4) Free from E. Coli and priority contaminants | G38: % of people in the commune | H38: In service - Needs training | I38: ="Mattson" -> Mattson | J38: Community, date, commune, Improved water source, accessible on premises, available when needed, free from E. Coli and priority contaminants | K38: Household WASH survey | L38: PMO | N38: On completion + annually | O38: Implementation monitoring console | R38: Household survey - Audit | S38: Third party contractor | T38: Every two years | U38: Third party audit console (TBD) | V38: The system validation form is more detailed and precise, but it is a sampled check on the reporting system
A39: Immediate outcome | B39: 2100 | C39: ='Log frame'!E17 -> Increased household access to sustainable, affordable, and safe drinking water services.​ | D39: 2100d | E39: % of intervention water points which are functional, potable, and have a balanced budget or a budget with surplus after 2 years | F39: Percentage of intervention water points that are functioning, potable, and financially sustainable (balanced or surplus budget) after 2 years of operation. 1a) Functional: Water point is in good working condition and regularly provides water according the specifications in the original design. OR 1b) Partially functional but in need of repair: Water point provides water on a regular basis (possibly in a reduced capacity) but repairs are needed due to some maintenance issue or change in conditions at the site. 2) "Potable": Free from E. Coli and priority contaminants, as measured by quarterly water potability tests performed by the Water Point Committee. 3) "financially sustainable (balanced or surplus budget)": See PPT presentation with definition of financial sustainability of the community-managed water points. 4) "after 2 years": Two years from the inauguration date of each intervention water point. | G39: % of intervention water points | H39: In service - Needs mods | I39: ="Mattson" -> Mattson | J39: Date, commune | K39: Water point survey | L39: PMO | N39: On completion + annually | O39: Implementation monitoring console | R39: Water point survey - Audit | S39: Third party contractor | T39: Every two years | U39: Third party audit console (TBD) | V39: The reporting and system validation forms are the same, just different deployments carried out by different stakeholders. Reporting: PMO. Validation: Third party contractor.
A40: Outputs | B40: 2110 | C40: ='Log frame'!E19 -> Develop community managed water points. | D40: 2110a | E40: # of people in intervention communes with access to basic drinking water service through community managed water points | F40: Number of people in intervention communes gaining access to basic drinking water service through community-managed water points built or rehabilitated by HANWASH and its partners. "Basic drinking water service": 1) Improved water source (according to the JMP classification) 2) Within 30 min round trip 3) [Household level] | G40: people | H40: In service - Needs training | I40: ="Mattson" -> Mattson | J40: Water point, gender, age category, improved water source, within 30 min round trip | K40: Water point survey | L40: PMO | N40: On completion | O40: Implementation monitoring console | R40: Household survey - Audit | S40: Third party contractor | T40: Every two years | U40: Third party audit console (TBD) | V40: The system validation form is more detailed and precise, but it is a sampled check on the reporting system
A41: Outputs | B41: 2110 | C41: ='Log frame'!E19 -> Develop community managed water points. | D41: 2110b | E41: # of community managed water points created | F41: Number of new community-managed water points created by HANWASH and its partners, with signed CPE bylaws with OREPA/DINEPA. "Community managed water points": 1) Signed CPE bylaws with OREPA/DINEPA | G41: water points | H41: In service - Needs training | I41: ="Mattson" -> Mattson | J41: Date, commune | K41: Implementation event tracking form | L41: PMO | N41: On completion | O41: Implementation monitoring console | R41: Household survey - Audit | S41: Third party contractor | T41: Every two years | U41: Third party audit console (TBD) | V41: The system validation form is more detailed and precise, but it is a sampled check on the reporting system
A42: Outputs | B42: 2110 | C42: Develop community managed water points. | D42: 2110c | E42: % of the community managed water points created which submit report to local authorities and OREPA on a monthly basis | F42: Percentage of newly created/rehabilitated community-managed water points that submit monthly reports to local authorities and OREPA, promoting accountability. | G42: water points | H42: In service - Needs training | I42: Mattson | J42: Date, commune | K42: Implementation event tracking form | L42: PMO | N42: Monthly | O42: Implementation monitoring console | P42: Household survey - Audit | Q42: Third party contractor | R42: Every two years | S42: Third party audit console (TBD) | T42: The system validation form is more detailed and precise, but it is a sampled check on the reporting system
A43: Outputs | B43: 2120 | C43: ='Log frame'!E21 -> Rehabilitate and expand professionally operated piped water systems. | D43: 2120a | E43: # of people added to safely managed drinking water service | F43: Number of people newly provided with safely managed drinking water service, meeting WHO/UNICEF Joint Monitoring Programme (JMP) criteria. "Safely managed drinking water service": 1) Improved water source (According to the JMP classification) 2) Available on premises 3) Available when needed 4) Free from E. Coli and priority contaminants, as measured by quarterly water quality testing performed by the Water Points Committees. | G43: people | H43: In service - Needs training | I43: ="Mattson" -> Mattson | J43: Water point, gender, age category, improved water source, available on premises, available when needed, free from E. Coli and priority contaminants | K43: SAEP monthly report | L43: PMO | N43: On completion | O43: Implementation monitoring console | R43: Household survey - Audit | S43: Third party contractor | T43: Every two years | U43: Third party audit console (TBD) | V43: The system validation form is more detailed and precise, but it is a sampled check on the reporting system
A44: Outputs | B44: 2120 | C44: Rehabilitate and expand professionally operated piped water systems. | D44: 2120c | E44: # of professionally managed piped water systems rehabilitated in the intervention communes | F44: Number of professionally managed piped water systems rehabilitated in the intervention communes, improving existing infrastructure. 1) "Professionally managed water systems": Signed OP bylaws with OREPA/DINEPA; 2)Rehabilitated: "The term "rehabilitated" implies that there was a pre-existing water supply system that may have been damaged, degraded, or in need of upgrades, and efforts were made to restore or enhance its functionality." | G44: water systems | H44: In service/Needs mods | I44: Mattson | J44: Water system, Date, commune | K44: Implementation event tracking form | L44: PMO | N44: On completion | O44: Implementation monitoring console | P44: Household survey - Audit | Q44: Third party contractor | R44: Review of existing data | S44: Third party audit console (TBD) | T44: Every two years
A45: Outputs | B45: 2120 | C45: ='Log frame'!E21 -> Rehabilitate and expand professionally operated piped water systems. | D45: 2120b | E45: # of professionally managed piped water systems created in the intervention communes | F45: Number of new professionally managed piped water systems created in the intervention communes, expanding access to safely managed drinking water service. "Professionally managed water systems": 1) Signed OP bylaws with OREPA/DINEPA | G45: water systems | H45: In service/Needs mods | I45: ="Mattson" -> Mattson | J45: Date, commune | K45: Implementation event tracking form | L45: PMO | N45: On completion | O45: Implementation monitoring console | R45: Household survey - Audit | S45: Third party contractor | T45: Every two years | U45: Third party audit console (TBD) | V45: The system validation form is more detailed and precise, but it is a sampled check on the reporting system
A46: Immediate outcome | B46: 2200 | C46: ='Log frame'!F17 -> Increased household access to sustainable, affordable, and safe sanitation services.​ | D46: 2200a | E46: % of intervention communities which are verified ODF | F46: Percentage of intervention communities verified as Open Defecation Free (ODF), by the commune WASH committee. "Verified ODF": 0) [Verification conducted by commune WASH committee] 1) 100% of households have a toilet that has been used at least once 2) Toilets meet the minimum standards of hygiene, privacy, and security and are in alignment with DINEPA's minimum standards 3) Areas of defecation identified during contact visits, reported no evidence of fecal matter 4) Schools attended by 80% of children comply with hygiene standards 5) Main market frequented by the population has a usable sanitary block or a formal step has been undertaken for this purpose 6) There is a willingness of the community to maintain a state of ODF | G46: % of intervention communities | H46: In service - Needs training | I46: ="Mattson" -> Mattson | J46: Date, commune | K46: ODF verification and certification | L46: PMO | N46: On completion | O46: Implementation monitoring console | R46: Household survey - Audit | S46: Third party contractor | T46: Every two years | U46: Third party audit console (TBD) | V46: The system validation form is more detailed and precise, but it is a sampled check on the reporting system
A47: Immediate outcome | B47: 2200 | C47: ='Log frame'!F17 -> Increased household access to sustainable, affordable, and safe sanitation services.​ | D47: 2200b | E47: % of population in intervention communes with at least basic sanitation service | F47: Percentage of population in intervention communes with access to at least basic sanitation service, defined as improved and unshared facilities. "...at least basic sanitation service": Basic 1) Improved (According to the JMP classification) 2) Unshared 3) [Household level] Note: Includes basic and safely managed sanitation service. | G47: % of people in the commune | H47: In service/Needs mods | I47: ="Mattson" -> Mattson | J47: Gender, age category, date, commune | K47: Household WASH survey | L47: PMO | N47: Launch + verification + certification | O47: Implementation monitoring console | R47: Household survey - Audit | S47: Third party contractor | T47: Every two years | U47: Third party audit console (TBD) | V47: The system validation form is more detailed and precise, but it is a sampled check on the reporting system
A48: Immediate outcome | B48: 2200 | C48: ='Log frame'!F17 -> Increased household access to sustainable, affordable, and safe sanitation services.​ | D48: 2200c | E48: % of population in intervention communes with safely managed sanitation service | F48: Percentage of population in intervention communes with access to safely managed sanitation service, meeting WHO/UNICEF JMP criteria. "Safely managed sanitation service": 1) Improved (according to the JMP classification) 2) Unshared AND 3a) Excreta treated in situ OR 3b) Excreta emptied, transported, and treated | G48: % of people in the commune | H48: In service/Needs mods | I48: ="Mattson" -> Mattson | J48: Gender, age category, date, commune | K48: Household WASH survey | L48: PMO | N48: Launch + verification + certification | O48: Implementation monitoring console | R48: Household survey - Audit | S48: Third party contractor | T48: Every two years | U48: Third party audit console (TBD) | V48: The system validation form is more detailed and precise, but it is a sampled check on the reporting system
A49: Outputs | B49: 2210 | C49: ='Log frame'!F19 -> Mobilize communities to achieve Open Defecation Free status | D49: 2210a | E49: # of people added to basic sanitation service in the intervention communes | F49: Number of people who newly gained access to basic sanitation service in the intervention communes, as a result of HANWASH interventions. "Basic sanitation service": 1) Improved (according to the JMP classification) 2) Unshared 3) [Household level] | G49: people | H49: In service/Needs mods | I49: ="Mattson" -> Mattson | J49: Gender, age category, date, commune | K49: Household WASH survey | L49: PMO | N49: On completion | O49: Implementation monitoring console | R49: Household survey - Audit | S49: Third party contractor | T49: Every two years | U49: Third party audit console (TBD) | V49: The system validation form is more detailed and precise, but it is a sampled check on the reporting system
A50: Outputs | B50: 2210 | C50: ='Log frame'!F19 -> Mobilize communities to achieve Open Defecation Free status | D50: 2210b | E50: # of "intervention" communities verified ODF | F50: Number of intervention communities verified as Open Defecation Free (ODF), by the commune WASH committee. "Verified ODF": 0) [Verification conducted by commune WASH committee] 1) 100% of households have a toilet that has been used at least once 2) Toilets meet the minimum standards of hygiene, privacy, and security and are in alignment with DINEPA's minimum standards 3) Areas of defecation identified during contact visits, reported no evidence of fecal matter 4) Schools attended by 80% of children comply with hygiene standards 5) Main market frequented by the population has a usable sanitary block or a formal step has been undertaken for this purpose 6) There is a willingness of the community to maintain a state of ODF | G50: communities | H50: In service/Needs mods | I50: ="Mattson" -> Mattson | J50: Community, date, commune | K50: ODF verification and certification | L50: Commune WASH committee | N50: On completion | O50: Implementation monitoring console | R50: Household survey - Audit | S50: Third party contractor | T50: Every two years | U50: Third party audit console (TBD) | V50: The system validation form is more detailed and precise, but it is a sampled check on the reporting system
A51: Outputs | B51: 2220 | C51: ='Log frame'!F21 -> Certify the sustained usage of sanitation services. | D51: 2220a | E51: # of "intervention" communities certified ODF | F51: Number of intervention communities that have been certified as Open Defecation Free (ODF) by the Communal Committee and OREPA, maintaining verified ODF status for at least one year. | G51: communities | H51: In service - Needs training | I51: ="Mattson" -> Mattson | J51: Community, date, commune | K51: ODF verification and certification | L51: Commune WASH committee | N51: Annually | O51: Implementation monitoring console | R51: Household survey - Audit | S51: Third party contractor | T51: Every two years | U51: Third party audit console (TBD) | V51: The system validation form is more detailed and precise, but it is a sampled check on the reporting system
A52: Outputs | B52: 2230 | C52: ='Log frame'!F23 -> Construct public latrines. | D52: 2230a | E52: # of public latrines constructed | F52: Number of public latrines constructed, improving sanitation access in communal areas. | G52: Public toilet blocks | H52: In service - Needs training | I52: HANWASH - Master | J52: Community, date, commune | K52: - | L52: PMO | N52: On completion | O52: Implementation monitoring console | R52: Household survey - Audit | S52: Third party contractor | T52: Every two years | U52: Third party audit console (TBD) | V52: IT IS UNCLEAR HOW THIS FITS INTO HANWASH'S VISION. HOW ARE THESE TOILET BLOCKS MANAGED? IF IT IS A "CASA", THEN THEY CAN BE MANAGED AS ODF COMMUNITIES INSTEAD OF STANDALONE TOILET BLOCKS.
A53: Immediate outcome | B53: 2300 | C53: ='Log frame'!G17 -> Increased household access to hygiene services. | D53: 2300a | E53: % of population in intervention communes with at least basic hygiene service | F53: Percentage of population in intervention communes with access to at least basic hygiene service, defined as presence of a handwashing facility with soap and water on premises. "...at least basic hygiene service" (according to the JMP classification): 1) Presence of a Hanwashing facility on premises 2) Presence of soap and water Notes: Also include people with access to hygiene services higher than basic. (we don't know yet what this looks like) | G53: % of people within intervention communities | H53: In service - Needs mods | I53: ="Mattson" -> Mattson | J53: Gender, age category | K53: Household WASH survey | L53: PMO | N53: Launch + verification + certification | O53: Implementation monitoring console | R53: Household survey - Audit | S53: Third party contractor | T53: Every two years | U53: Third party audit console (TBD) | V53: The Household survey - Audit is more detailed and precise, but it is a sampled check on the reporting system
A54: Immediate outcome | B54: 2300 | C54: ='Log frame'!G17 -> Increased household access to hygiene services. | D54: 2300b | E54: % of population in intervention communes with basic hygiene service | F54: Percentage of population in intervention communes with access to basic hygiene service, as defined by WHO/UNICEF JMP criteria. "Basic hygiene service": 1) Presence of a Hanwashing facility on premises 2) Presence of soap and water | G54: % of people in the commune | H54: In service - Needs mods | I54: ="Mattson" -> Mattson | J54: Gender, age category | K54: Household WASH survey | L54: PMO | N54: Launch + verification + certification | O54: Implementation monitoring console | R54: Household survey - Audit | S54: Third party contractor | T54: Every two years | U54: Third party audit console (TBD) | V54: The Household survey - Audit is more detailed and precise, but it is a sampled check on the reporting system
A55: Outputs | B55: 2310 | C55: ='Log frame'!G19 -> Train skilled community animators to deliver hygiene trainings and community mobilization.​ | D55: 2310a | E55: # of community animators trained | F55: Number of community animators/coaches trained to provide leadership and WASH training to people in the intervention communities. | G55: animators/coaches | H55: In service - Needs mods | I55: ="Mattson" -> Mattson | J55: Date, commune | K55: Implementation event tracking form | L55: PMO | N55: After every training event | O55: Implementation monitoring console | R55: Review of existing data | S55: Third party contractor | T55: Every two years | U55: Implementation monitoring console | V55: System validation consists of a sampled desk review of reported data
A56: Outputs | B56: 2310 | C56: Train skilled community animators to deliver hygiene trainings and community mobilization.​ | D56: 2310b | E56: # of hours of hygiene trainings and community mobilization provided by the community animators trained | F56: Cumulative number of hours of leadership and WASH training delivered by trained community animators/coaches. This indicator measures the intensity of leadership and WASH training delivered by the community animators. It is the sum of hours the community animator spends providing those trainings to people in the intervention communities. | G56: Cumulative number of hours of training | H56: Not started | I56: Mattson | J56: Date, commune, communities | K56: Implementation event tracking form | L56: PMO | N56: After every training event | O56: Implementation monitoring console | P56: Review of existing data | Q56: Third party contractor | R56: Review of existing data | S56: HANWASH M&E officer | T56: System validation consists of a sampled desk review of reported data | U56: Implementation monitoring console
A57: Outputs | B57: 2320 | C57: ='Log frame'!G21 -> Certify the sustained usage of hygiene services. | D57: 2320a | E57: # of people added to basic hygiene service | F57: Number of people newly gaining access to basic hygiene service in the intervention communes as a result of HANWASH and partners interventions. "Basic hygiene service": 1) Presence of a handwashing facility on premises 2) Presence of soap and water 3) [Household level] | G57: people | H57: In service - Needs mods | I57: ="Mattson" -> Mattson | J57: Date, commune | K57: ODF verification and certification | L57: PMO | N57: After every training event | O57: Implementation monitoring console | R57: Review of existing data | S57: Third party contractor | T57: Every two years | U57: Implementation monitoring console | V57: System validation consists of a sampled desk review of reported data
A58: Immediate outcome | B58: 2400 | C58: ='Log frame'!H17 -> Increased access to sustainable, safe drinking water, sanitation, and hygiene materials in healthcare facilities, schools, and public places. | D58: 2400a | E58: % of schools with basic drinking water, sanitation, and hygiene services | F58: Percentage of schools in intervention communes with basic drinking water, sanitation, and hygiene services, meeting WHO/UNICEF JMP criteria for schools. '"Basic drinking water service": 1) Improved 2) Currently available "Basic sanitation service": 1) Improved 2) Usable 3) Gender separated toilets available "Basic hygiene service": 1) Presence of handwashing facilities 2) Presence of soap and water | G58: % of total number of schools in intervention communes | H58: In service - Needs training | I58: HANWASH - Master | J58: Water service level, sanitation service level, hygiene service level, date, commune | K58: School WASH form | L58: PMO | N58: On completion + annually | O58: Implementation monitoring console | R58: School WASH form - Audit | S58: Third party contractor | T58: Every two years | U58: Third party audit console (TBD) | V58: The reporting and system validation forms are the same, just different deployments carried out by different stakeholders. Reporting: PMO. Validation: Third party contractor.
A59: Immediate outcome | B59: 2400 | C59: ='Log frame'!H17 -> Increased access to sustainable, safe drinking water, sanitation, and hygiene materials in healthcare facilities, schools, and public places. | D59: 2400b | E59: % of healthcare facilities with basic drinking water, sanitation, and hygiene services | F59: Percentage of healthcare facilities in intervention areas with basic drinking water, sanitation, and hygiene services, meeting WHO/UNICEF JMP criteria for healthcare facilities. "Basic drinking water service": 1) Improved 2) On premises 3) Currently available "Basic sanitation service": 1) Improved 2) Usable 3) Dedicated for staff 4) Sex-separated with menstrual hygiene facilities 5) Accessible for users with limited mobility "Basic hygiene service": ...At points of care 1) Facilities present 2) Soap and water or alcohol based hand rub present ...At toilets 1) Within 5 m of toilets 2) Facilities present 3) Soap and water present | G59: % of total number of healthcare facilities in intervention communes | H59: In service - Needs training | I59: HANWASH - Master | J59: Water service level, sanitation service level, hygiene service level, date, commune | K59: Healthcare facility WASH form | L59: PMO | N59: On completion + annually | O59: Implementation monitoring console | R59: Healthcare facility WASH form - Audit | S59: Third party contractor | T59: Every two years | U59: Third party audit console (TBD) | V59: The reporting and system validation forms are the same, just different deployments carried out by different stakeholders. Reporting: PMO. Validation: Third party contractor.
A60: Outputs | B60: 2410 | C60: ='Log frame'!H19 -> Construct or rehabilitate water supply for healthcare facilities and schools. | D60: 2410a | E60: # of schools added with basic drinking water services | F60: Number of schools newly provided with basic drinking water services in intervention communes, as a result of HANWASH and partners' interventions, meeting WHO/UNICEF JMP criteria for schools. "Basic drinking water service": 1) Improved 2) Currently available 3) potable | G60: schools | H60: In service - Needs training | I60: HANWASH - Master | J60: Water service level, date, commune | K60: School WASH form | L60: PMO | N60: On completion + annually | O60: Implementation monitoring console | R60: School WASH form - Audit | S60: Third party contractor | T60: Every two years | U60: Third party audit console (TBD) | V60: The reporting and system validation forms are the same, just different deployments carried out by different stakeholders. Reporting: PMO. Validation: Third party contractor.
A61: Outputs | B61: 2410 | C61: ='Log frame'!H19 -> Construct or rehabilitate water supply for healthcare facilities and schools. | D61: 2410b | E61: # of healthcare facilities added with basic drinking water services | F61: Number of healthcare facilities newly provided with basic drinking water services in intervention communes, as a result of HANWASH and partners' interventions, meeting WHO/UNICEF JMP criteria for healthcare facilities. "Basic drinking water service": 1) Improved 2) On premises 3) Currently available 4) Potable | G61: healthcare facilities | H61: In service - Needs training | I61: HANWASH - Master | J61: Water service level, date, commune | K61: Healthcare facility WASH form | L61: PMO | N61: On completion + annually | O61: Implementation monitoring console | R61: Healthcare facility WASH form - Audit | S61: Third party contractor | T61: Every two years | U61: Third party audit console (TBD) | V61: The reporting and system validation forms are the same, just different deployments carried out by different stakeholders. Reporting: PMO. Validation: Third party contractor.
A62: Outputs | B62: 2420 | C62: ='Log frame'!H21 -> Construct communal, healthcare facility, and school latrines. | D62: 2420a | E62: # of schools added with basic sanitation services | F62: Number of schools newly provided with basic sanitation services in the intervention communes, as a result of HANWASH and partners' interventions, meeting WHO/UNICEF JMP criteria for schools. "Basic sanitation service": 1) Improved 2) Usable 3) Gender separated toilets available | G62: schools | H62: In service - Needs training | I62: HANWASH - Master | J62: Sanitation service level, date, commune | K62: School WASH form | L62: PMO | N62: On completion + annually | O62: Implementation monitoring console | R62: School WASH form - Audit | S62: Third party contractor | T62: Every two years | U62: Third party audit console (TBD) | V62: The reporting and system validation forms are the same, just different deployments carried out by different stakeholders. Reporting: PMO. Validation: Third party contractor.
A63: Outputs | B63: 2420 | C63: ='Log frame'!H21 -> Construct communal, healthcare facility, and school latrines. | D63: 2420b | E63: # of healthcare facilities added with basic sanitation services | F63: Number of healthcare facilities newly provided with basic sanitation services in the intervention communes, as a result of HANWASH and partners' interventions, meeting WHO/UNICEF JMP criteria for healthcare facilities. "Basic sanitation services": 1) Improved 2) Usable 3) Separated for staff and patients 4) Gender separated with menstrual hygiene facilities 5) Accessible for users with limited mobility | G63: healthcare facilities | H63: In service - Needs training | I63: HANWASH - Master | J63: Sanitation service level, date, commune | K63: Healthcare facility WASH form | L63: PMO | N63: On completion + annually | O63: Implementation monitoring console | R63: Healthcare facility WASH form - Audit | S63: Third party contractor | T63: Every two years | U63: Third party audit console (TBD) | V63: The reporting and system validation forms are the same, just different deployments carried out by different stakeholders. Reporting: PMO. Validation: Third party contractor.
A64: Outputs | B64: 2430 | C64: ='Log frame'!H23 -> Work with (local authorities, civil society) to ensure access to soap or alcohol-based handrub at schools and healthcare facilities. | D64: 2430a | E64: # of schools added with basic hygiene | F64: Number of schools newly provided with basic hygiene services in the intervention communes, as a result of HANWASH and partners' interventions, meeting WHO/UNICEF JMP criteria for schools. "Basic hygiene": 1) Presence of handwashing facilities 2) Presence of soap and water | G64: schools | H64: In service - Needs training | I64: HANWASH - Master | J64: Hygiene servicec level, date, commune | K64: School WASH form | L64: PMO | N64: On completion + annually | O64: Implementation monitoring console | R64: School WASH form - Audit | S64: Third party contractor | T64: Every two years | U64: Third party audit console (TBD) | V64: The reporting and system validation forms are the same, just different deployments carried out by different stakeholders. Reporting: PMO. Validation: Third party contractor.
A65: Outputs | B65: 2430 | C65: ='Log frame'!H23 -> Work with (local authorities, civil society) to ensure access to soap or alcohol-based handrub at schools and healthcare facilities. | D65: 2430b | E65: # of healthcare facilities added with basic hygiene | F65: Number of healthcare facilities newly provided with basic hygiene services in the intervention communes, as a result of HANWASH and partners' interventions, meeting WHO/UNICEF JMP criteria for healthcare facilities. "Basic hygiene": ...At points of care 1) Facilities present 2) Soap and water or alcohol based hand rub present ...At toilets 1) Within 5 m of toilets 2) Facilities present 3) Soap and water present | G65: healthcare facilities | H65: In service - Needs training | I65: HANWASH - Master | J65: Hygiene service level, date, commune | K65: Healthcare facility WASH form | L65: PMO | N65: On completion + annually | O65: Implementation monitoring console | R65: Healthcare facility WASH form - Audit | S65: Third party contractor | T65: Every two years | U65: Third party audit console (TBD) | V65: The reporting and system validation forms are the same, just different deployments carried out by different stakeholders. Reporting: PMO. Validation: Third party contractor.
A66: Intermediate outcome | B66: 3000 | C66: ='Log frame'!I15 -> Expanded reach and resources leveraged through collective action with other national and international actors.​ | D66: - | E66: - | F66: - | G66: - | H66: - | I66: ="Mattson" -> Mattson | J66: - | K66: - | L66: - | N66: - | O66: - | P66: - | Q66: - | R66: - | S66: - | T66: - | U66: - | V66: This objective is split into its component objectives and measured via their indicators
A67: Immediate outcome | B67: 3100 | C67: ='Log frame'!I17 -> Increased government and non-government funding in alignment with HANWASH Core Values. | D67: 3100a | E67: Cumulative amount of money committed in alignment with HANWASH Core Values | F67: Cumulative amount of money (in USD) committed to projects aligned with HANWASH Core Values: local leadership, collaboration, systematic approach, impact, and commitment. Aligned with HANWASH Core Values: **LOCALLY LED** We strengthen community participation in governance of WASH infrastructure and services. **COLLABORATIVE** Volunteers, government authorities, and partners are meaningfully engaged, and a MOU is signed among the parties. ### **SYSTEMATIC** We will be thoughtful and consistent in planning, doing, and improving our work.** **IMPACTFUL** Sustainability is a key metric of our success. **COMMITTED** We will not stop until the job is done. | G67: USD | H67: In service | I67: ="Mattson" -> Mattson | J67: Actor, project type date, commune | K67: HANWASH project monitoring | L67: HANWASH M&E Officer | N67: Annually | O67: Project monitoring console | R67: Review of existing data | S67: HANWASH M&E Officer & DINEPA | T67: Annually | U67: Project monitoring console | V67: Since this indicator is completed by the HANWASH M&E officer, HANWASH should review the results with DINEPA as a check on the reporting system
A68: Immediate outcome | B68: 3100 | C68: ='Log frame'!I17 -> Increased government and non-government funding in alignment with HANWASH Core Values. | D68: 3100b | E68: % of committed money which has been spent (cumulative) | F68: Percentage of committed funds that have been spent, calculated as (Cumulative_amount_spent / Cumulative_amount_committed) * 100. | G68: % of amount committeed | H68: In service - Needs training | I68: Mattson | J68: Commune, project, date | K68: HANWASH project monitoring | L68: HANWASH M&E Officer | N68: Annually | O68: Project monitoring console | R68: Review of existing data | S68: Third party contractor | T68: Every two years | U68: Third party audit console (TBD) | V68: System validation consists of a sampled desk review of reported data
A69: Outputs | B69: 3110 | C69: ='Log frame'!I19 -> Mobilize and coordinate funding from government and non-government sources in HANWASH program areas in alignment with HANWASH Core Values. | D69: 3110a | E69: Amount of money spent by external actors within HANWASH project areas | F69: Cumulative amount of money (in USD) spent by external (non-rotarian) actors within HANWASH project areas, aligned with HANWASH Core Values. | G69: USD | H69: In service | I69: ="Mattson" -> Mattson | J69: Actor, date, commune | K69: HANWASH project monitoring | L69: HANWASH M&E Officer | N69: Annually | O69: Project monitoring console | R69: Review of existing data | S69: HANWASH M&E Officer & DINEPA | T69: Annually | U69: Project monitoring console | V69: Since this indicator is completed by the HANWASH M&E officer, HANWASH should review the results with DINEPA as a check on the reporting system
A70: Outputs | B70: 3120 | C70: ='Log frame'!I21 -> Mobilize and influence funding from government and non-government sources beyond HANWASH program areas in alignment with HANWASH Core Values. | D70: 3120a | E70: Amount of money spent by external actors beyond project areas in alignment with HANWASH Core Values | F70: Cumulative amount of money (in USD) spent by external (non-rotarian) actors beyond HANWASH project areas but still within the WASH sector and aligned with HANWASH Core Values, extending impact. | G70: USD | H70: In service | I70: HANWASH - Master | J70: Actor, date, commune | K70: HANWASH project monitoring | L70: HANWASH M&E Officer | N70: Annually | O70: Project monitoring console | R70: Review of existing data | S70: HANWASH M&E Officer & DINEPA | T70: Annually | U70: Project monitoring console | V70: Since this indicator is completed by the HANWASH M&E officer, HANWASH should review the results with DINEPA as a check on the reporting system
A71: Immediate outcome | B71: 3200 | C71: ='Log frame'!J17 -> Increased capacity of DINEPA to regulate the sector and OREPA to oversee and support implementation. | D71: 3200a | E71: % of implementing partners in HANWASH program areas who have signed the DINEPA Accord Cadre | F71: Percentage of implementing partners in HANWASH program areas who have signed the DINEPA Accord Cadre, ensuring alignment with national standards. (Number of IPs who have signed the Accord Cadre / Total number of IPs in HANWASH program areas) x 100 | G71: % of implementing partners in HANWASH program areas | H71: In service - Needs mods | I71: ="Mattson" -> Mattson | J71: Post/position, commune, department, date | K71: SIEPA Accord Cadre | L71: HANWASH M&E Officer | N71: Annually | O71: - | P71: - | Q71: - | R71: - | S71: - | T71: - | U71: - | V71: Since this information is contained in SIEPA, the HANWASH M&E Officer should work with ONEPA to aquire the data. Validation
A72: Outputs | B72: 3210 | C72: ='Log frame'!J19 -> Conduct leadership training of DINEPA and OREPA personnel. | D72: 3210a | E72: # of DINEPA personnel trained as leaders | F72: Number of DINEPA personnel who have completed leadership training, building capacity within the national water authority. | G72: people | H72: In service - Needs training | I72: ="Mattson" -> Mattson | J72: Gender, date, commune | K72: Implementation event tracking form | L72: PMO | N72: After every training event | O72: Implementation monitoring console | R72: Review of existing data | S72: HANWASH M&E officer | T72: Quarterly | U72: Implementation monitoring console | V72: System validation consists of a sampled desk review of reported data
A73: Outputs | B73: 3220 | C73: ='Log frame'!J21 -> Provide technical assistance and training to DINEPA and the OREPAs. | D73: 3220a | E73: # of technical trainings provided for DINEPA priority areas | F73: Number of technical trainings provided for DINEPA priority areas, focusing on key topics such as unified national tariff methodology and ODF certification. Priorities areas for 2023-24: Unified national tariff methodology & ODF certification. Priorities areas for 2024-2025: ? Priorities areas for 2025-2026: ? | G73: trainings | H73: In service - Needs training | I73: ="Mattson" -> Mattson | J73: Date, commune | K73: Implementation event tracking form | L73: PMO | N73: After every assistance or training event | O73: Implementation monitoring console | R73: Review of existing data | S73: HANWASH M&E officer | T73: Quarterly | U73: Implementation monitoring console | V73: System validation consists of a sampled desk review of reported data

Sheet Indicator-Mayors
A1: Organization: HANWASH | E1: Legend
A2: Document: Indicator framework | E2: TBD' To be determined | F2: ="'-' Not applicable" -> '-' Not applicable
A3: Objective: Define indicators to measure progress towards each objective.
A4: Scope: HANWASH programs | E4: Objective types | F4: Description
A5: Reference link: This document | E5: Ultimate outcome | F5: The highest level objective of HANWASH. These are not directly measureable by SMART indicators, but measured indirectly via indicators of their component Intermediate Outcomes.
A6: Version number: 3 | E6: Intermediate outcome | F6: The component objectives of the HANWASH ultimate outcome. These are not directly measureable by SMART indicators, but measured indirectly via indicators of their component Intermediate Outcomes.
A7: Version date: June 30, 2025 | E7: Immediate outcome | F7: The higher level objective that HANWASH seeks to achieve, which are able to be measured directly by SMART indicators. Indicators measuring these outcomes are typically expressed as a percent, which are harder to measure, but builds the context into the measure.
A8: Notes: SMART indicators are indicators which are specific, measureable, achievable, relevant, and time-bound. | E8: Output | F8: The lower level objective that HANWASH seeks to achieve. Indicators measuring these outcomes are typically expressed as a number, which is easier to measure, but also easier to take out of context.
A10: Objective | D10: Indicator | K10: Data collection | P10: Commune validation | R10: Data validation and Reporting | V10: Notes
A11: Type | B11: Code | C11: Description | D11: Code_index | E11: Description | F11: Definitions | G11: Units | H11: Status | I11: Program | J11: (Dis)Aggregation | K11: Source | L11: Enumerator | M11: Type of data collection | N11: Frequency | O11: Visualization | P11: Data source | Q11: Data collection | R11: Source | S11: Data Validator | T11: Reporting Frequency | U11: Visualization
A12: Ultimate outcome | B12: 1 | C12: ='Log frame'!B13 -> Increased access to safe, sustainable and affordable water, sanitation and hygiene (WASH) services in Haiti​. | D12: - | E12: - | F12: - | G12: - | H12: - | I12: ="Mattson" -> Mattson | J12: - | K12: - | L12: - | N12: - | O12: - | P12: - | Q12: - | R12: - | S12: - | T12: - | U12: - | V12: This objective is split into its component objectives and measured via their indicators
A13: Intermediate outcome | B13: 1000 | C13: ='Log frame'!B15 -> Strengthened demand for and management of WASH services in communes. | D13: - | E13: - | F13: - | G13: - | H13: - | I13: ="Mattson" -> Mattson | J13: - | K13: - | L13: - | N13: - | O13: - | P13: - | Q13: - | R13: - | S13: - | T13: - | U13: - | V13: This objective is split into its component objectives and measured via their indicators
A14: Immediate outcome | B14: 1100 | C14: ='Log frame'!B17 -> Increased civil society engagement in decision making and implementation of WASH services. | D14: 1100a | E14: % of on-site commune WASH events with Haitian Rotarian participation | F14: Percentage of commune-level WASH events that have active Haitian Rotarians participation, measured as a proportion of total reported events. | G14: % of total commune level WASH events reported | H14: In service - Needs training | I14: ="Mattson" -> Mattson | J14: Event type, participant group, date, commune | K14: Implementation event tracking form | L14: M&E RC Focal points | M14: Secondary | N14: Monthly | O14: Implementation monitoring console | R14: Interview with the Mayors and the RC Presidents | S14: HANWASH M&E Manager | T14: Semi-annually | U14: Implementation monitoring console | V14: System validation consists of an exhaustive desk review of both the PMO and Rotarians forms.
A15: Immediate outcome | B15: 1100 | C15: Increased civil society engagement in decision making and implementation of WASH services. | D15: 1100b | E15: Proportion (%) of paricipants in the virtual WASH projects meetings which are Haitian rotarians | F15: % of total number of participants in WASH project team meeting which are Haitian rotarians (disaggregated by RC) (Host club should set the target) | G15: % of total number of participants in WASH project team meeting | H15: Not started | I15: Mattson | J15: Event type, participant group, date, commune | K15: Implementation event tracking form | L15: M&E RC Focal points | M15: Secondary | N15: Monthly | O15: Implementation monitoring console | P15: Review of existing data | Q15: HANWASH M&E Manager | R15: Review of existing data from virtual meeting record. | S15: HANWASH M&E Manager | T15: Semi-annually | U15: Implementation monitoring console
A16: Outputs | B16: 1110 | C16: Support civil society engagement in the WASH sector.​ | D16: 1110a | E16: # of field visits conducted quarterly by Rotarians in the intervention communities | F16: Total number of field visits conducted quarterly by Rotarians in the intervention communities. | G16: # of field visits | H16: In service - Needs training | I16: ="Mattson" -> Mattson | J16: Event type, participant group, date, commune | K16: Implementation event tracking form | L16: M&E RC Focal points | M16: Secondary | N16: Monthly | O16: Implementation monitoring console | R16: Review of existing data | S16: HANWASH M&E Manager | T16: Semi-annually | U16: Implementation monitoring console | V16: System validation consists of an exhaustive desk review of both the PMO and Rotarians forms.
A17: Immediate outcome | B17: 1200 | C17: ='Log frame'!C17 -> Improved commune WASH planning and coordination by local authorities.​ | D17: 1200a | E17: % of approved interventions implemented in alignment with Commune Action Plans | F17: Percentage of the interventions that have received formal approval/assignment from the Mayors offices through a demand letter or other written documents which have been implemented or are in-process by HANWASH or its partners. The approved interventions are subsets of the commune action plans which are assigned to HANWASH or its partners by the Mayor's Offices. | G17: % of implemented activities | H17: In service - Needs mods | I17: ="Mattson" -> Mattson | J17: Date, commune | K17: Activities form | L17: Mayors | M17: Secondary | N17: Semi-annually | O17: Project monitoring console | P17: Commune action plan | Q17: Commune WASH committee | R17: Review of existing data | S17: HANWASH M&E Manager | T17: Semi-annually | U17: Project monitoring console | V17: It's critical that "Activities" planned by HANWASH correspond to those in the commune action plan in the system.
A18: Outputs | B18: 1210 | C18: ='Log frame'!C19 -> Create or improve commune action plans that focus on water, sanitation and hygiene, and water resource management.​ | D18: 1210a | E18: # of communes with action plans that explicitly include each W,S,H,WRM aspect (water, sanitation, hygiene, water resources management) | F18: Number of communes with comprehensive action plans that explicitly address all four WASH aspects: Water, Sanitation, Hygiene, and Water Resources Management. | G18: communes | H18: In service - Needs mods | I18: ="Mattson" -> Mattson | J18: Date, commune | K18: Activities form | L18: Mayors | M18: Secondary | N18: Annually | O18: Project monitoring console | R18: Review of existing data | S18: HANWASH M&E Manager | T18: Annually | U18: Project monitoring console | V18: System validation consists of an exhaustive desk review of reported data
A19: Outputs | B19: 1220 | C19: ='Log frame'!C21 -> Facilitate coordination meetings between commune WASH stakeholders. | D19: 1220a | E19: # of WASH planning and coordination events with DINEPA and municipal officials | F19: Number of WASH planning and coordination events conducted with DINEPA and municipal officials per month, fostering collaboration and alignment. | G19: events/month | H19: In service - Needs training | I19: ="Mattson" -> Mattson | J19: Event type, participant group, date, commune | K19: Implementation event tracking form | L19: Mayors & Partner of Implementation | M19: Secondary | N19: Monthly | O19: Implementation monitoring console | R19: Review of existing data | S19: HANWASH M&E Manager | T19: Semi-annually | U19: Implementation monitoring console | V19: System validation consists of a sampled desk review of reported data
A20: Immediate outcome | B20: 1300 | C20: ='Log frame'!D17 -> Improved accountability of service providers to users of WASH services.​ | D20: 1300a | E20: % of service providers under HANWASH initiative monitored according to DINEPA/OREPA guidelines as accepted by the Mayor's Office | F20: A service provider is defined as the management structure in charge of a water system (“SAEP”) or a community-managed well (“CPE”). This indicator measures the % of service providers regularly (i.e. monthly) submitting reports to DINEPA and local authorities, according to the DINEPA's requirements in terms of indicators to be captured and data to be shared. | G20: % of the total number of service providers which received the HANWASH intervention in the target communes | H20: In service - Needs mods | I20: Mattson | J20: Water point/system, date, commune | K20: Water point survey and SAEP monthly report | L20: OREPA focal points | M20: Secondary | N20: Monthly | O20: Implementation monitoring console | R20: Water point survey - Audit | S20: OREPA Focal Points & HANWASH M&E Manager | T20: Semi-annually | U20: Third party audit console (TBD) | V20: The reporting and system validation forms are the same, just different deployments carried out by different stakeholders. Reporting: PMO. Validation: Third party contractor.
A21: Immediate outcome | B21: 1300 | C21: ='Log frame'!D17 -> Improved accountability of service providers to users of WASH services.​ | D21: 1300b | E21: % of intervention service providers which are 100% accountable per DINEPA/OREPA and the Mayor's requirements | F21: Percentage of intervention service providers that have a score of accountability of 11 out of 11. The service provider is 100% accountable if: 1) CPE or Operator team meets regularly (see OREPA bylaws) 2) CPE or Operator meets with community regularly (see OREPA bylaws) 3) CPE or Operator signed bylaws with OREPA and apply them 4) Water usage fees are collected on a monthly basis from the subscribers 5) Deposits are made on a monthly basis on the bank account and records are available; 6) Reports are submitted to OREPA and the local authorities on a monthly basis 7) Water treatment is done regularly, in alignment with OREPA's requirements 8) Water potability test is done at the water points or the water system regularly, in alignment with OREPA's requirements (at least once every quarter for the community water points) 9) Number of days out of service in the event of a water infrastructure breakdown doesn't exceed five days. 10) The service provider pays monthly to OREPA a percentage of the total revenue being collected (see OREPA bylaws) 11) Election is held every three years to renew the CPE members | G21: % of intervention water points | H21: In service - Needs mods | I21: ="Mattson" -> Mattson | J21: Water point, date, commune | K21: Accountability Evaluation Form (TBD) | L21: Mayors & OREPA focal points | M21: Secondary | N21: Annually | O21: Implementation monitoring console | P21: Water point survey | R21: Water point survey - Audit | S21: OREPA Focal Points & HANWASH M&E Manager | T21: Annually | U21: Third party audit console (TBD) | V21: The reporting and system validation forms are the same, just different deployments carried out by different stakeholders. Reporting: PMO. Validation: Third party contractor.
A22: Immediate outcome | B22: 1300 | C22: Improved accountability of service providers to users of WASH services.​ | D22: 1300c | E22: % of users being satisfied with the quality, affordability and reliability of the WASH services provided | F22: This indicator measures the proportion of the water customers from the intervention communes which are satisfied with the quality, affordability and reliability of the WASH services provided | G22: % of households connected to the water systems | H22: Not started | I22: Mattson | J22: Water point, commune | K22: Subscribers Satisfaction Survey (TBD) | L22: Water Service provider | M22: Primary (on-site survey) | N22: Annually | O22: Implementation monitoring console | P22: Water point survey - Audit | Q22: Third party contractor | R22: Field data collection | S22: OREPA Focal Points & HANWASH M&E Manager | T22: Annually | U22: Implementation monitoring console
A23: Outputs | B23: 1310 | C23: ='Log frame'!D19 -> Monitor WASH service performance and satisfaction. | D23: 1310a | E23: Average number of days to resolve breakdown of the water infrastructures | F23: This indicator measures how long it takes on average for the service providers to resolve breakdown of the water infrastructure. The indicator is disaggregated by type of management structure in charge of the water infrastructures: CPEs, CAEPA/CTE/OP. | G23: Days | H23: Not started | I23: ="Mattson" -> Mattson | J23: Water system, date, commune | K23: SAEP monthly report, Water point survey | L23: Water service provider | M23: Secondary | N23: Monthly | O23: Implementation monitoring console | R23: Review of existing data | S23: OREPA Focal Points & HANWASH M&E Manager | T23: Semi-annually | U23: Implementation monitoring console | V23: System validation consists of a sampled desk review of reported data
A24: Outputs | B24: 1310 | C24: =C23 -> Monitor WASH service performance and satisfaction. | D24: 1310b | E24: Average number of days of drinking water service provided during the month by the service providers | F24: This indicator measures the average number of days of drinking water service provided to the users during the month by the service providers. The indicator is disaggregated by type of management structure in charge of the water infrastructures: CPEs, CAEPA/CTE/OP. | G24: Days | H24: Not started | I24: ="Mattson" -> Mattson | J24: Water system, date, commune | K24: SAEP monthly report, Water point survey | L24: Water service provider | M24: Secondary | N24: Monthly | O24: Implementation monitoring console | R24: Review of existing data | S24: OREPA Focal Points & HANWASH M&E Manager | T24: Semi-annually | U24: Implementation monitoring console | V24: System validation consists of a sampled desk review of reported data
A25: Outputs | B25: 1310 | C25: =C24 -> Monitor WASH service performance and satisfaction. | D25: 1310c | E25: Number of on-site inspection visits conducted annually by OREPA in the intervention communes | F25: This indicator measures the number of on-site inspection visits conducted annually by OREPA in the intervention communes | G25: on-site inspection visits | K25: OREPA's field inspection reports (TBD) | L25: OREPA focal points | N25: Quarterly | R25: Review of OREPA's field inspection reports | S25: OREPA Focal Points | T25: Semi-annually
A26: Outputs | B26: 1310 | C26: =C25 -> Monitor WASH service performance and satisfaction. | D26: 1310d | E26: Water fee collection rate (disaggregated by type of service providers) | F26: The percentage of the total water user fees that were successfully collected from subscribers by the service providers within a quarter, compared to the total amount billed or expected during that period. This indicator is disaggregated by type of service provider (CPE, professional operator, CAEPA, CTE). | G26: % of total amount of water fees billed or expected during the quarter | J26: CPE, professional operator, CAEPA, CTE | K26: SAEP monthly report, Water point survey | L26: Water Service provider | M26: Secondary | N26: Monthly | S26: OREPA Focal Points & HANWASH M&E Manager | T26: Semi-annually
A27: Outputs | B27: 1320 | C27: ='Log frame'!D21 -> Review service provider performance with stakeholders. | D27: 1320a | E27: # of communes which have held an annual service provider review with key stakeholders in the last year | F27: This indicator measures the number of communes within the program area that have conducted at least one formal, documented annual review meeting in the past 12 months to assess the performance of water and sanitation service providers. The review must involve key stakeholders, including the Commune Committee (CASEC/ASEC or local authorities), users (e.g., representatives of community water users), service providers (e.g., water system operators), and implementing partners (e.g., NGOs, donors, or government agencies involved in WASH service delivery). Key Criteria for Counting a Commune as Having Met the Indicator: 1) A service provider performance review meeting was held within the last 12 months. 2) The meeting was convened or co-organized by the commune authority or another recognized coordinating body. 3) Representatives from all five stakeholder groups (OREPA, Commune Committee, users, service providers, implementing partners) were invited and at least three attended. 4) The meeting included a structured agenda covering topics such as service quality, financial performance, user satisfaction, and challenges. 5) Meeting minutes or a summary report was produced and made available to participants. | G27: communes | H27: In service - Needs mods | I27: ="Mattson" -> Mattson | J27: Water system, date, commune | K27: SAEP monthly report | L27: Mayors & Water service provider | M27: Secondary | N27: Annually | O27: Implementation monitoring console | R27: - | S27: OREPA Focal Points & HANWASH M&E Manager | T27: Annually | U27: Implementation monitoring console | V27: System validation consists of a sampled desk review of reported data
A28: Intermediate outcome | B28: 2000 | C28: ='Log frame'!E15 -> Enhanced household access to and use of sustainable, affordable, and safe water, sanitation and hygiene services.​ | D28: - | E28: - | F28: - | G28: - | H28: - | I28: ="Mattson" -> Mattson | J28: - | K28: - | L28: - | N28: - | O28: - | P28: - | Q28: - | R28: - | S28: - | T28: - | U28: - | V28: This objective is split into its component objectives and measured via their indicators
A29: Immediate outcome | B29: 2100 | C29: ='Log frame'!E17 -> Increased household access to sustainable, affordable, and safe drinking water services.​ | D29: 2100b | E29: % of population in intervention communes with at least basic drinking water service | F29: Percentage of population in intervention communes with access to at least basic drinking water service, defined as an improved water source within 30 minutes round trip. "...at least basic drinking water service": 1) Improved water source (according to the JMP classification) 2) Within 30 min round trip Note: This also includes basic and safely managed water service. | G29: % of people in the commune | H29: In service - Needs training | I29: ="Mattson" -> Mattson | J29: Community, date, commune, improved water source, within 30 min round trip | K29: Household WASH survey | L29: Partner of implementation | M29: Primary (on-site survey) | N29: Annually | O29: Implementation monitoring console | R29: Household survey - Audit | S29: OREPA Focal Points & HANWASH M&E Manager | T29: Annually | U29: Third party audit console (TBD) | V29: The system validation form is more detailed and precise, but it is a sampled check on the reporting system
A30: Immediate outcome | B30: 2100 | C30: ='Log frame'!E17 -> Increased household access to sustainable, affordable, and safe drinking water services.​ | D30: 2100c | E30: % of population in intervention communes with safely managed drinking water service | F30: Percentage of population in intervention communes with access to safely managed drinking water service, defined as an improved water source accessible on premises, available when needed, and free from contamination. "Safely managed drinking water service": 1) Improved water source (according to the JMP classification) 2) Accessible on premises 3) Available when needed 4) Free from E. Coli and priority contaminants | G30: % of people in the commune | H30: In service - Needs training | I30: ="Mattson" -> Mattson | J30: Community, date, commune, Improved water source, accessible on premises, available when needed, free from E. Coli and priority contaminants | K30: Household WASH survey | L30: Partner of implementation | M30: Primary (on-site survey) | N30: Annually | O30: Implementation monitoring console | R30: Household survey - Audit | S30: OREPA Focal Points & HANWASH M&E Manager | T30: Annually | U30: Third party audit console (TBD) | V30: The system validation form is more detailed and precise, but it is a sampled check on the reporting system
A31: Immediate outcome | B31: 2100 | C31: ='Log frame'!E17 -> Increased household access to sustainable, affordable, and safe drinking water services.​ | D31: 2100d | E31: % of intervention water points which are functional, potable, and have a balanced budget or a budget with surplus after 2 years | F31: Percentage of intervention water points that are functioning, potable, and financially sustainable (balanced or surplus budget) after 2 years of operation. 1a) Functional: Water point is in good working condition and regularly provides water according the specifications in the original design. OR 1b) Partially functional but in need of repair: Water point provides water on a regular basis (possibly in a reduced capacity) but repairs are needed due to some maintenance issue or change in conditions at the site. 2) "Potable": Free from E. Coli and priority contaminants, as measured by quarterly water potability tests performed by the Water Point Committee. 3) "financially sustainable (balanced or surplus budget)": See PPT presentation with definition of financial sustainability of the community-managed water points. 4) "after 2 years": Two years from the inauguration date of each intervention water point. | G31: % of intervention water points | H31: In service - Needs mods | I31: ="Mattson" -> Mattson | J31: Date, commune | K31: Water point survey | L31: Partner of implementation | M31: Primary (on-site survey) | N31: Semi-annually | O31: Implementation monitoring console | R31: Water point survey - Audit | S31: OREPA Focal Points & HANWASH M&E Manager | T31: Annually | U31: Third party audit console (TBD) | V31: The reporting and system validation forms are the same, just different deployments carried out by different stakeholders. Reporting: PMO. Validation: Third party contractor.
A32: Outputs | B32: 2110 | C32: ='Log frame'!E19 -> Develop community managed water points. | D32: 2110a | E32: # of people added to basic drinking water service through community managed water points | F32: Number of people in intervention communes gaining access to basic drinking water service through community-managed water points built or rehabilitated by HANWASH and its partners. "Basic drinking water service": 1) Improved water source (according to the JMP classification) 2) Within 30 min round trip 3) [Household level] | G32: people | H32: In service - Needs training | I32: ="Mattson" -> Mattson | J32: Water point, gender, age category, improved water source, within 30 min round trip | K32: Water point survey | L32: Partner of implementation | M32: Primary (on-site survey) | N32: Semi-annually | O32: Implementation monitoring console | R32: Household survey - Audit | S32: HANWASH M&E Manager | T32: Semi-annually | U32: Third party audit console (TBD) | V32: The system validation form is more detailed and precise, but it is a sampled check on the reporting system
A33: Outputs | B33: 2120 | C33: ='Log frame'!E21 -> Rehabilitate and expand professionally operated piped water systems. | D33: 2120a | E33: # of people added to safely managed drinking water service through water systems newly created or rehabilitated in the intervention communes | F33: Number of people newly provided with safely managed drinking water service, meeting WHO/UNICEF Joint Monitoring Programme (JMP) criteria. "Safely managed drinking water service": 1) Improved water source (According to the JMP classification) 2) Available on premises 3) Available when needed 4) Free from E. Coli and priority contaminants, as measured by quarterly water quality testing performed by the Water Points Committees. | G33: people | H33: In service - Needs training | I33: ="Mattson" -> Mattson | J33: Newly created or rehabilitated Water systems, gender, category of subscribers | K33: SAEP monthly report | L33: Partner of implementation | M33: Secondary | N33: Semi-annually | O33: Implementation monitoring console | R33: Household survey - Audit | S33: HANWASH M&E Manager | T33: Semi-annually | U33: Third party audit console (TBD) | V33: The system validation form is more detailed and precise, but it is a sampled check on the reporting system
A34: Immediate outcome | B34: 2200 | C34: ='Log frame'!F17 -> Increased household access to sustainable, affordable, and safe sanitation services.​ | D34: 2200a | E34: % of intervention communities which are verified ODF (Open Defecation Free) | F34: Percentage of intervention communities verified as Open Defecation Free (ODF), by the commune WASH committee. "Verified ODF": 0) [Verification conducted by commune WASH committee] 1) 100% of households have a toilet that has been used at least once 2) Toilets meet the minimum standards of hygiene, privacy, and security and are in alignment with DINEPA's minimum standards 3) Areas of defecation identified during contact visits, reported no evidence of fecal matter 4) Schools attended by 80% of children comply with hygiene standards 5) Main market frequented by the population has a usable sanitary block or a formal step has been undertaken for this purpose 6) There is a willingness of the community to maintain a state of ODF | G34: % of total # of intervention communities | H34: In service - Needs training | I34: ="Mattson" -> Mattson | J34: Date, commune | K34: ODF verification and certification Form | L34: Commune WASH committee | M34: Primary (on-site survey) | N34: Semi-annually | O34: Implementation monitoring console | R34: Household survey - Audit | S34: Mayors & HANWASH M&E Manager | T34: Semi-annually | U34: Third party audit console (TBD) | V34: The system validation form is more detailed and precise, but it is a sampled check on the reporting system
A35: Immediate outcome | B35: 2200 | C35: =C34 -> Increased household access to sustainable, affordable, and safe sanitation services.​ | D35: 2200b | E35: % of "intervention" communities which are certified ODF (Open Defecation Free) | F35: Percentage of intervention communities that have been certified as Open Defecation Free (ODF) by the Communal Committee and OREPA, maintaining verified ODF status for at least one year. | G35: % of total # of intervention communities | H35: In service - Needs training | I35: ="Mattson" -> Mattson | J35: Community, date, commune | K35: ODF verification and certification Form | L35: Commune WASH committee & OREPA Focal Points | M35: Primary (on-site survey) | N35: Annually | O35: Implementation monitoring console | R35: Household survey - Audit | S35: OREPA Focal Points & HANWASH M&E Manager | T35: Annually | U35: Third party audit console (TBD) | V35: The system validation form is more detailed and precise, but it is a sampled check on the reporting system
A36: Immediate outcome | B36: 2200 | C36: ='Log frame'!F17 -> Increased household access to sustainable, affordable, and safe sanitation services.​ | D36: 2200c | E36: % of population in intervention communes with at least basic sanitation service | F36: Percentage of population in intervention communes with access to at least basic sanitation service, defined as improved and unshared facilities. "...at least basic sanitation service": Basic 1) Improved (According to the JMP classification) 2) Unshared 3) [Household level] Note: Includes basic and safely managed sanitation service. | G36: % of total # of people in the commune | H36: In service/Needs mods | I36: ="Mattson" -> Mattson | J36: Gender, age category, date, commune | K36: Household WASH survey | L36: Partner of implementation | M36: Primary (on-site survey) | N36: Launch + verification + certification | O36: Implementation monitoring console | R36: Household survey - Audit | S36: Mayors & OREPA Focal Points & HANWASH M&E Manager | T36: Annually | U36: Third party audit console (TBD) | V36: The system validation form is more detailed and precise, but it is a sampled check on the reporting system
A37: Outputs | B37: 2210 | C37: ='Log frame'!F19 -> Mobilize communities to achieve Open Defecation Free status | D37: 2210a | E37: # of people added to basic sanitation service in the intervention communes | F37: Number of people who newly gained access to basic sanitation service in the intervention communes, as a result of HANWASH interventions. "Basic sanitation service": 1) Improved (according to the JMP classification) 2) Unshared 3) [Household level] | G37: people | H37: In service/Needs mods | I37: ="Mattson" -> Mattson | J37: Gender, age category, date, commune | K37: Household WASH survey | L37: Partner of implementation | M37: Primary (on-site survey) | N37: Monthly | O37: Implementation monitoring console | R37: Household survey - Audit | S37: HANWASH M&E Manager | T37: Semi-annually | U37: Third party audit console (TBD) | V37: The system validation form is more detailed and precise, but it is a sampled check on the reporting system
A38: Outputs | B38: 2230 | C38: ='Log frame'!F23 -> Construct public latrines. | D38: 2230a | E38: # of public latrines constructed | F38: Number of public latrines constructed, improving sanitation access in communal areas. | G38: Public toilet blocks | H38: In service - Needs training | I38: HANWASH - Master | J38: Community, date, commune | K38: Public latrine form | L38: Partner of implementation | M38: Secondary | N38: Semi-annually | O38: Implementation monitoring console | R38: Household survey - Audit | S38: OREPA Focal Points & HANWASH M&E Manager | T38: Semi-annually | U38: Third party audit console (TBD) | V38: IT IS UNCLEAR HOW THIS FITS INTO HANWASH'S VISION. HOW ARE THESE TOILET BLOCKS MANAGED? IF IT IS A "CASA", THEN THEY CAN BE MANAGED AS ODF COMMUNITIES INSTEAD OF STANDALONE TOILET BLOCKS.
A39: Immediate outcome | B39: 2300 | C39: ='Log frame'!G17 -> Increased household access to hygiene services. | D39: 2300a | E39: % of population in intervention communes with at least basic hygiene service | F39: Percentage of population in intervention communes with access to at least basic hygiene service, defined as presence of a handwashing facility with soap and water on premises. "...at least basic hygiene service" (according to the JMP classification): 1) Presence of a Hanwashing facility on premises 2) Presence of soap and water Notes: Also include people with access to hygiene services higher than basic. (we don't know yet what this looks like) | G39: % of people within intervention communities | H39: In service - Needs mods | I39: ="Mattson" -> Mattson | J39: Gender, age category | K39: Household WASH survey | L39: Partner of implementation | M39: Primary (on-site survey) | N39: Launch + verification + certification | O39: Implementation monitoring console | R39: Household survey - Audit | S39: Mayors & OREPA Focal Points & HANWASH M&E Manager | T39: Semi-annually | U39: Third party audit console (TBD) | V39: The Household survey - Audit is more detailed and precise, but it is a sampled check on the reporting system
A40: Outputs | B40: 2310 | C40: ='Log frame'!G19 -> Train skilled community animators to deliver hygiene trainings and community mobilization.​ | D40: 2310a | E40: # of community animators trained | F40: Number of community animators/coaches trained to provide leadership and WASH training to people in the intervention communities. | G40: animators/coaches | H40: In service - Needs mods | I40: ="Mattson" -> Mattson | J40: Date, commune | K40: Training sessions tracking form (TBD) | L40: Partner of implementation | M40: Primary (on-site survey) | N40: Quarterly | O40: Implementation monitoring console | R40: Review of existing data | S40: Mayors & HANWASH M&E Manager | T40: Semi-annually | U40: Implementation monitoring console | V40: System validation consists of a sampled desk review of reported data
A41: Outputs | B41: 2310 | C41: Train skilled community animators to deliver hygiene trainings and community mobilization.​ | D41: 2310b | E41: # of hours of hygiene trainings and community mobilization provided by the community animators trained | F41: Cumulative number of hours of leadership and WASH training delivered by trained community animators/coaches. This indicator measures the intensity of leadership and WASH training delivered by the community animators. It is the sum of hours the community animator spends providing those trainings to people in the intervention communities. | G41: Cumulative number of hours of training | H41: Not started | I41: Mattson | J41: Date, commune, communities | K41: Training sessions tracking form | L41: Partner of implementation | M41: Secondary | N41: Monthly | O41: Implementation monitoring console | P41: Review of existing data | Q41: Third party contractor | R41: Review of existing data | S41: HANWASH M&E Manager | T41: Semi-annually | U41: Implementation monitoring console
A42: Outputs | B42: 2320 | C42: ='Log frame'!G21 -> Certify the sustained usage of hygiene services. | D42: 2320a | E42: # of people added to basic hygiene service | F42: Number of people newly gaining access to basic hygiene service in the intervention communes as a result of HANWASH and partners interventions. "Basic hygiene service": 1) Presence of a handwashing facility on premises 2) Presence of soap and water 3) [Household level] | G42: people | H42: In service - Needs mods | I42: ="Mattson" -> Mattson | J42: Date, commune | K42: ODF verification and certification Form | L42: Partner of implementation | M42: Primary (on-site survey) | N42: Monthly | O42: Implementation monitoring console | R42: Review of existing data | S42: OREPA Focal Points & HANWASH M&E Manager | T42: Semi-annually | U42: Implementation monitoring console | V42: System validation consists of a sampled desk review of reported data
A43: Immediate outcome | B43: 2400 | C43: ='Log frame'!H17 -> Increased access to sustainable, safe drinking water, sanitation, and hygiene materials in healthcare facilities, schools, and public places. | D43: 2400a | E43: % of schools with at least basic drinking water, sanitation, and hygiene services | F43: Percentage of schools in intervention communes with basic drinking water, sanitation, and hygiene services, meeting WHO/UNICEF JMP criteria for schools. '"Basic drinking water service": 1) Improved 2) Currently available "Basic sanitation service": 1) Improved 2) Usable 3) Gender separated toilets available "Basic hygiene service": 1) Presence of handwashing facilities 2) Presence of soap and water | G43: % of total number of schools in intervention communes | H43: In service - Needs training | I43: HANWASH - Master | J43: Water service level, sanitation service level, hygiene service level, date, commune | K43: School WASH form | L43: Partner of implementation | M43: Primary (on-site survey) | N43: Annually | O43: Implementation monitoring console | R43: School WASH form - Audit | S43: OREPA Focal Points & HANWASH M&E Manager | T43: Annually | U43: Third party audit console (TBD) | V43: The reporting and system validation forms are the same, just different deployments carried out by different stakeholders. Reporting: PMO. Validation: Third party contractor.
A44: Immediate outcome | B44: 2400 | C44: ='Log frame'!H17 -> Increased access to sustainable, safe drinking water, sanitation, and hygiene materials in healthcare facilities, schools, and public places. | D44: 2400b | E44: % of healthcare facilities with at least basic drinking water, sanitation, and hygiene services | F44: Percentage of healthcare facilities in intervention areas with basic drinking water, sanitation, and hygiene services, meeting WHO/UNICEF JMP criteria for healthcare facilities. "Basic drinking water service": 1) Improved 2) On premises 3) Currently available "Basic sanitation service": 1) Improved 2) Usable 3) Dedicated for staff 4) Sex-separated with menstrual hygiene facilities 5) Accessible for users with limited mobility "Basic hygiene service": ...At points of care 1) Facilities present 2) Soap and water or alcohol based hand rub present ...At toilets 1) Within 5 m of toilets 2) Facilities present 3) Soap and water present | G44: % of total number of healthcare facilities in intervention communes | H44: In service - Needs training | I44: HANWASH - Master | J44: Water service level, sanitation service level, hygiene service level, date, commune | K44: Healthcare facility WASH form | L44: Partner of implementation | M44: Primary (on-site survey) | N44: Annually | O44: Implementation monitoring console | R44: Healthcare facility WASH form - Audit | S44: OREPA Focal Points & HANWASH M&E Manager | T44: Annually | U44: Third party audit console (TBD) | V44: The reporting and system validation forms are the same, just different deployments carried out by different stakeholders. Reporting: PMO. Validation: Third party contractor.
A45: Outputs | B45: 2410 | C45: ='Log frame'!H19 -> Construct or rehabilitate water supply for healthcare facilities and schools. | D45: 2410a | E45: # of schools added with basic drinking water services | F45: Number of schools newly provided with basic drinking water services in intervention communes, as a result of HANWASH and partners' interventions, meeting WHO/UNICEF JMP criteria for schools. "Basic drinking water service": 1) Improved 2) Currently available 3) potable | G45: schools | H45: In service - Needs training | I45: HANWASH - Master | J45: Water service level, date, commune | K45: School WASH form | L45: Partner of implementation | M45: Primary (on-site survey) | N45: Semi-annually | O45: Implementation monitoring console | R45: School WASH form - Audit | S45: OREPA Focal Points & HANWASH M&E Manager | T45: Annually | U45: Third party audit console (TBD) | V45: The reporting and system validation forms are the same, just different deployments carried out by different stakeholders. Reporting: PMO. Validation: Third party contractor.
A46: Outputs | B46: 2410 | C46: ='Log frame'!H19 -> Construct or rehabilitate water supply for healthcare facilities and schools. | D46: 2410b | E46: # of healthcare facilities added with basic drinking water services | F46: Number of healthcare facilities newly provided with basic drinking water services in intervention communes, as a result of HANWASH and partners' interventions, meeting WHO/UNICEF JMP criteria for healthcare facilities. "Basic drinking water service": 1) Improved 2) On premises 3) Currently available 4) Potable | G46: healthcare facilities | H46: In service - Needs training | I46: HANWASH - Master | J46: Water service level, date, commune | K46: Healthcare facility WASH form | L46: Partner of implementation | M46: Primary (on-site survey) | N46: Semi-annually | O46: Implementation monitoring console | R46: Healthcare facility WASH form - Audit | S46: OREPA Focal Points & HANWASH M&E Manager | T46: Annually | U46: Third party audit console (TBD) | V46: The reporting and system validation forms are the same, just different deployments carried out by different stakeholders. Reporting: PMO. Validation: Third party contractor.
A47: Outputs | B47: 2420 | C47: ='Log frame'!H21 -> Construct communal, healthcare facility, and school latrines. | D47: 2420a | E47: # of schools added with basic sanitation services | F47: Number of schools newly provided with basic sanitation services in the intervention communes, as a result of HANWASH and partners' interventions, meeting WHO/UNICEF JMP criteria for schools. "Basic sanitation service": 1) Improved 2) Usable 3) Gender separated toilets available | G47: schools | H47: In service - Needs training | I47: HANWASH - Master | J47: Sanitation service level, date, commune | K47: School WASH form | L47: Partner of implementation | M47: Primary (on-site survey) | N47: Semi-annually | O47: Implementation monitoring console | R47: School WASH form - Audit | S47: OREPA Focal Points & HANWASH M&E Manager | T47: Annually | U47: Third party audit console (TBD) | V47: The reporting and system validation forms are the same, just different deployments carried out by different stakeholders. Reporting: PMO. Validation: Third party contractor.
A48: Outputs | B48: 2420 | C48: ='Log frame'!H21 -> Construct communal, healthcare facility, and school latrines. | D48: 2420b | E48: # of healthcare facilities added with basic sanitation services | F48: Number of healthcare facilities newly provided with basic sanitation services in the intervention communes, as a result of HANWASH and partners' interventions, meeting WHO/UNICEF JMP criteria for healthcare facilities. "Basic sanitation services": 1) Improved 2) Usable 3) Separated for staff and patients 4) Gender separated with menstrual hygiene facilities 5) Accessible for users with limited mobility | G48: healthcare facilities | H48: In service - Needs training | I48: HANWASH - Master | J48: Sanitation service level, date, commune | K48: Healthcare facility WASH form | L48: Partner of implementation | M48: Primary (on-site survey) | N48: Semi-annually | O48: Implementation monitoring console | R48: Healthcare facility WASH form - Audit | S48: OREPA Focal Points & HANWASH M&E Manager | T48: Annually | U48: Third party audit console (TBD) | V48: The reporting and system validation forms are the same, just different deployments carried out by different stakeholders. Reporting: PMO. Validation: Third party contractor.
A49: Outputs | B49: 2430 | C49: ='Log frame'!H23 -> Work with (local authorities, civil society) to ensure access to soap or alcohol-based handrub at schools and healthcare facilities. | D49: 2430a | E49: # of schools added with basic hygiene | F49: Number of schools newly provided with basic hygiene services in the intervention communes, as a result of HANWASH and partners' interventions, meeting WHO/UNICEF JMP criteria for schools. "Basic hygiene": 1) Presence of handwashing facilities 2) Presence of soap and water | G49: schools | H49: In service - Needs training | I49: HANWASH - Master | J49: Hygiene servicec level, date, commune | K49: School WASH form | L49: Partner of implementation | M49: Primary (on-site survey) | N49: Semi-annually | O49: Implementation monitoring console | R49: School WASH form - Audit | S49: OREPA Focal Points & HANWASH M&E Manager | T49: Annually | U49: Third party audit console (TBD) | V49: The reporting and system validation forms are the same, just different deployments carried out by different stakeholders. Reporting: PMO. Validation: Third party contractor.
A50: Outputs | B50: 2430 | C50: ='Log frame'!H23 -> Work with (local authorities, civil society) to ensure access to soap or alcohol-based handrub at schools and healthcare facilities. | D50: 2430b | E50: # of healthcare facilities added with basic hygiene | F50: Number of healthcare facilities newly provided with basic hygiene services in the intervention communes, as a result of HANWASH and partners' interventions, meeting WHO/UNICEF JMP criteria for healthcare facilities. "Basic hygiene": ...At points of care 1) Facilities present 2) Soap and water or alcohol based hand rub present ...At toilets 1) Within 5 m of toilets 2) Facilities present 3) Soap and water present | G50: healthcare facilities | H50: In service - Needs training | I50: HANWASH - Master | J50: Hygiene service level, date, commune | K50: Healthcare facility WASH form | L50: Partner of implementation | M50: Primary (on-site survey) | N50: Semi-annually | O50: Implementation monitoring console | R50: Healthcare facility WASH form - Audit | S50: OREPA Focal Points & HANWASH M&E Manager | T50: Annually | U50: Third party audit console (TBD) | V50: The reporting and system validation forms are the same, just different deployments carried out by different stakeholders. Reporting: PMO. Validation: Third party contractor.
A51: Intermediate outcome | B51: 3000 | C51: ='Log frame'!I15 -> Expanded reach and resources leveraged through collective action with other national and international actors.​ | D51: - | E51: - | F51: - | G51: - | H51: - | I51: ="Mattson" -> Mattson | J51: - | K51: - | L51: - | N51: - | O51: - | P51: - | Q51: - | R51: - | S51: - | T51: - | U51: - | V51: This objective is split into its component objectives and measured via their indicators
A52: Immediate outcome | B52: 3100 | C52: ='Log frame'!I17 -> Increased government and non-government funding in alignment with HANWASH Core Values. | D52: 3100a | E52: Cumulative amount of money committed in alignment with HANWASH Core Values, supported by an MOU signed with HANWASH | F52: Cumulative amount of money (in USD) committed to projects aligned with HANWASH Core Values: local leadership, collaboration, systematic approach, impact, and commitment. Aligned with HANWASH Core Values: **LOCALLY LED** We strengthen community participation in governance of WASH infrastructure and services. **COLLABORATIVE** Volunteers, government authorities, and partners are meaningfully engaged, and a MOU is signed among the parties. ### **SYSTEMATIC** We will be thoughtful and consistent in planning, doing, and improving our work.** **IMPACTFUL** Sustainability is a key metric of our success. **COMMITTED** We will not stop until the job is done. | G52: USD | H52: In service | I52: ="Mattson" -> Mattson | J52: Actor, project type date, commune | K52: HANWASH financial records & MOU signed with partners | L52: HANWASH CFO | M52: Secondary | N52: Annually | O52: Project monitoring console | R52: Review of existing data | S52: HANWASH Country Director | T52: Annually | U52: Project monitoring console | V52: Since this indicator is completed by the HANWASH M&E Manager, HANWASH should review the results with DINEPA as a check on the reporting system
A53: Immediate outcome | B53: 3100 | C53: ='Log frame'!I17 -> Increased government and non-government funding in alignment with HANWASH Core Values. | D53: 3100b | E53: % of committed money which has been spent (cumulative), supported by an MOU signed with HANWASH | F53: Percentage of committed funds that have been spent, calculated as (Cumulative_amount_spent / Cumulative_amount_committed) * 100. | G53: % of amount committeed | H53: In service - Needs training | I53: Mattson | J53: Commune, project, date | K53: HANWASH financial records & MOU signed with partners | L53: HANWASH CFO | M53: Secondary | N53: Annually | O53: Project monitoring console | R53: Review of existing data | S53: HANWASH Country Director | T53: Annually | U53: Third party audit console (TBD) | V53: System validation consists of a sampled desk review of reported data
A54: Outputs | B54: 3110 | C54: ='Log frame'!I19 -> Mobilize and coordinate funding from government and non-government sources in HANWASH program areas in alignment with HANWASH Core Values. | D54: 3110a | E54: Amount of money spent by external actors within HANWASH project areas, supported by an MOU signed with HANWASH The term "project areas" refers to the geographic locations or regions where a specific project is being implemented or where project activities are taking place. | F54: Cumulative amount of money (in USD) spent by external (non-rotarian) actors within HANWASH project areas, aligned with HANWASH Core Values. | G54: USD | H54: In service | I54: ="Mattson" -> Mattson | J54: Actor, date, commune | K54: HANWASH financial records & MOU signed with partners | L54: HANWASH CFO | M54: Secondary | N54: Annually | O54: Project monitoring console | R54: Review of existing data | S54: HANWASH Country Director | T54: Annually | U54: Project monitoring console | V54: Since this indicator is completed by the HANWASH M&E Manager, HANWASH should review the results with DINEPA as a check on the reporting system
A55: Outputs | B55: 3120 | C55: ='Log frame'!I21 -> Mobilize and influence funding from government and non-government sources beyond HANWASH program areas in alignment with HANWASH Core Values. | D55: 3120a | E55: Amount of money spent by external actors beyond project areas in alignment with HANWASH Core Values, supported by an MOU signed with HANWASH The term "project areas" refers to the geographic locations or regions where a specific project is being implemented or where project activities are taking place. | F55: Cumulative amount of money (in USD) spent by external (non-rotarian) actors beyond HANWASH project areas but still within the WASH sector and aligned with HANWASH Core Values, extending impact. | G55: USD | H55: In service | I55: HANWASH - Master | J55: Actor, date, commune | K55: HANWASH financial records & MOU signed with partners | L55: HANWASH CFO | M55: Secondary | N55: Annually | O55: Project monitoring console | R55: Review of existing data | S55: HANWASH Country Director | T55: Annually | U55: Project monitoring console | V55: Since this indicator is completed by the HANWASH M&E Manager, HANWASH should review the results with DINEPA as a check on the reporting system
A56: Immediate outcome | B56: 3200 | C56: ='Log frame'!J17 -> Increased capacity of DINEPA to regulate the sector and OREPA to oversee and support implementation. | D56: 3200a | E56: % of implementing partners in HANWASH program areas who have signed the DINEPA Accord Cadre | F56: Percentage of implementing partners in HANWASH program areas who have signed the DINEPA Accord Cadre, ensuring alignment with national standards. (Number of IPs who have signed the Accord Cadre / Total number of IPs in HANWASH program areas) x 100 | G56: % of implementing partners in HANWASH program areas | H56: In service - Needs mods | I56: ="Mattson" -> Mattson | J56: Post/position, commune, department, date | K56: SIEPA Accord Cadre | L56: HANWASH Country Director | M56: Secondary | N56: Annually | O56: - | P56: - | Q56: - | R56: - | S56: OREPA Focal Points | T56: Annually | U56: - | V56: Since this information is contained in SIEPA, the HANWASH M&E Manager should work with ONEPA to aquire the data. Validation
A57: Outputs | B57: 3220 | C57: ='Log frame'!J21 -> Provide technical assistance and training to DINEPA and the OREPAs. | D57: 3220a | E57: # of technical trainings provided for DINEPA priority areas | F57: Number of technical trainings provided for DINEPA priority areas, focusing on key topics such as unified national tariff methodology and ODF certification. Priorities areas for 2023-24: Unified national tariff methodology & ODF certification. Priorities areas for 2024-2025: ? Priorities areas for 2025-2026: ? | G57: trainings | H57: In service - Needs training | I57: ="Mattson" -> Mattson | J57: Date, commune | K57: Implementation event tracking form | L57: Partner of implementation | M57: Secondary | N57: Quarterly | O57: Implementation monitoring console | R57: Review of existing data | S57: HANWASH M&E Manager | T57: Semi-annually | U57: Implementation monitoring console | V57: System validation consists of a sampled desk review of reported data

Sheet Indicator-Implementing partner
A1: Organization: HANWASH | E1: Legend
A2: Document: Indicator framework | E2: TBD' To be determined | F2: ="'-' Not applicable" -> '-' Not applicable
A3: Objective: Define indicators to measure progress towards each objective.
A4: Scope: HANWASH programs | E4: Objective types | F4: Description
A5: Reference link: This document | E5: Ultimate outcome | F5: The highest level objective of HANWASH. These are not directly measureable by SMART indicators, but measured indirectly via indicators of their component Intermediate Outcomes.
A6: Version number: 3 | E6: Intermediate outcome | F6: The component objectives of the HANWASH ultimate outcome. These are not directly measureable by SMART indicators, but measured indirectly via indicators of their component Intermediate Outcomes.
A7: Version date: June 30, 2025 | E7: Immediate outcome | F7: The higher level objective that HANWASH seeks to achieve, which are able to be measured directly by SMART indicators. Indicators measuring these outcomes are typically expressed as a percent, which are harder to measure, but builds the context into the measure.
A8: Notes: SMART indicators are indicators which are specific, measureable, achievable, relevant, and time-bound. | E8: Output | F8: The lower level objective that HANWASH seeks to achieve. Indicators measuring these outcomes are typically expressed as a number, which is easier to measure, but also easier to take out of context.
A10: Objective | D10: Indicator | K10: Data collection | P10: Commune validation | R10: Data validation and Reporting | V10: Notes
A11: Type | B11: Code | C11: Description | D11: Code_index | E11: Description | F11: Definitions | G11: Units | H11: Status | I11: Program | J11: (Dis)Aggregation | K11: Source | L11: Enumerator | M11: Type of data collection | N11: Frequency | O11: Visualization | P11: Data source | Q11: Data collection | R11: Source | S11: Data Validator | T11: Reporting Frequency | U11: Visualization
A12: Ultimate outcome | B12: 1 | C12: ='Log frame'!B13 -> Increased access to safe, sustainable and affordable water, sanitation and hygiene (WASH) services in Haiti​. | D12: - | E12: - | F12: - | G12: - | H12: - | I12: ="Mattson" -> Mattson | J12: - | K12: - | L12: - | N12: - | O12: - | P12: - | Q12: - | R12: - | S12: - | T12: - | U12: - | V12: This objective is split into its component objectives and measured via their indicators
A13: Intermediate outcome | B13: 1000 | C13: ='Log frame'!B15 -> Strengthened demand for and management of WASH services in communes. | D13: - | E13: - | F13: - | G13: - | H13: - | I13: ="Mattson" -> Mattson | J13: - | K13: - | L13: - | N13: - | O13: - | P13: - | Q13: - | R13: - | S13: - | T13: - | U13: - | V13: This objective is split into its component objectives and measured via their indicators
A14: Immediate outcome | B14: 1100 | C14: ='Log frame'!B17 -> Increased civil society engagement in decision making and implementation of WASH services. | D14: 1100a | E14: % of on-site commune WASH events with Haitian Rotarian participation | F14: Percentage of commune-level WASH events that have active Haitian Rotarians participation, measured as a proportion of total reported events. | G14: % of total commune level WASH events reported | H14: In service - Needs training | I14: ="Mattson" -> Mattson | J14: Event type, participant group, date, commune | K14: Implementation event tracking form | L14: M&E RC Focal points | M14: Secondary | N14: Monthly | O14: Implementation monitoring console | R14: Interview with the Mayors and the RC Presidents | S14: HANWASH M&E Manager | T14: Semi-annually | U14: Implementation monitoring console | V14: System validation consists of an exhaustive desk review of both the PMO and Rotarians forms.
A15: Immediate outcome | B15: 1100 | C15: Increased civil society engagement in decision making and implementation of WASH services. | D15: 1100b | E15: Proportion (%) of paricipants in the virtual WASH projects meetings which are Haitian rotarians | F15: % of total number of participants in WASH project team meeting which are Haitian rotarians (disaggregated by RC) (Host club should set the target) | G15: % of total number of participants in WASH project team meeting | H15: Not started | I15: Mattson | J15: Event type, participant group, date, commune | K15: Implementation event tracking form | L15: M&E RC Focal points | M15: Secondary | N15: Monthly | O15: Implementation monitoring console | P15: Review of existing data | Q15: HANWASH M&E Manager | R15: Review of existing data from virtual meeting record. | S15: HANWASH M&E Manager | T15: Semi-annually | U15: Implementation monitoring console
A16: Outputs | B16: 1110 | C16: Support civil society engagement in the WASH sector.​ | D16: 1110a | E16: # of field visits conducted quarterly by Rotarians in the intervention communities | F16: Total number of field visits conducted quarterly by Rotarians in the intervention communities. | G16: # of field visits | H16: In service - Needs training | I16: ="Mattson" -> Mattson | J16: Event type, participant group, date, commune | K16: Implementation event tracking form | L16: M&E RC Focal points | M16: Secondary | N16: Monthly | O16: Implementation monitoring console | R16: Review of existing data | S16: HANWASH M&E Manager | T16: Semi-annually | U16: Implementation monitoring console | V16: System validation consists of an exhaustive desk review of both the PMO and Rotarians forms.
A17: Immediate outcome | B17: 1200 | C17: ='Log frame'!C17 -> Improved commune WASH planning and coordination by local authorities.​ | D17: 1200a | E17: % of approved interventions implemented in alignment with Commune Action Plans | F17: Percentage of the interventions that have received formal approval/assignment from the Mayors offices through a demand letter or other written documents which have been implemented or are in-process by HANWASH or its partners. The approved interventions are subsets of the commune action plans which are assigned to HANWASH or its partners by the Mayor's Offices. | G17: % of implemented activities | H17: In service - Needs mods | I17: ="Mattson" -> Mattson | J17: Date, commune | K17: Activities form | L17: Mayors | M17: Secondary | N17: Semi-annually | O17: Project monitoring console | P17: Commune action plan | Q17: Commune WASH committee | R17: Review of existing data | S17: HANWASH M&E Manager | T17: Semi-annually | U17: Project monitoring console | V17: It's critical that "Activities" planned by HANWASH correspond to those in the commune action plan in the system.
A18: Outputs | B18: 1210 | C18: ='Log frame'!C19 -> Create or improve commune action plans that focus on water, sanitation and hygiene, and water resource management.​ | D18: 1210a | E18: # of communes with action plans that explicitly include each W,S,H,WRM aspect (water, sanitation, hygiene, water resources management) | F18: Number of communes with comprehensive action plans that explicitly address all four WASH aspects: Water, Sanitation, Hygiene, and Water Resources Management. | G18: communes | H18: In service - Needs mods | I18: ="Mattson" -> Mattson | J18: Date, commune | K18: Activities form | L18: Mayors | M18: Secondary | N18: Annually | O18: Project monitoring console | R18: Review of existing data | S18: HANWASH M&E Manager | T18: Annually | U18: Project monitoring console | V18: System validation consists of an exhaustive desk review of reported data
A19: Outputs | B19: 1220 | C19: ='Log frame'!C21 -> Facilitate coordination meetings between commune WASH stakeholders. | D19: 1220a | E19: # of WASH planning and coordination events with DINEPA and municipal officials | F19: Number of WASH planning and coordination events conducted with DINEPA and municipal officials per month, fostering collaboration and alignment. | G19: events/month | H19: In service - Needs training | I19: ="Mattson" -> Mattson | J19: Event type, participant group, date, commune | K19: Implementation event tracking form | L19: Mayors & Partner of Implementation | M19: Secondary | N19: Monthly | O19: Implementation monitoring console | R19: Review of existing data | S19: HANWASH M&E Manager | T19: Semi-annually | U19: Implementation monitoring console | V19: System validation consists of a sampled desk review of reported data
A20: Immediate outcome | B20: 1300 | C20: ='Log frame'!D17 -> Improved accountability of service providers to users of WASH services.​ | D20: 1300a | E20: % of service providers under HANWASH initiative monitored according to DINEPA/OREPA guidelines as accepted by the Mayor's Office | F20: A service provider is defined as the management structure in charge of a water system (“SAEP”) or a community-managed well (“CPE”). This indicator measures the % of service providers regularly (i.e. monthly) submitting reports to DINEPA and local authorities, according to the DINEPA's requirements in terms of indicators to be captured and data to be shared. | G20: % of the total number of service providers which received the HANWASH intervention in the target communes | H20: In service - Needs mods | I20: Mattson | J20: Water point/system, date, commune | K20: Water point survey and SAEP monthly report | L20: OREPA focal points | M20: Secondary | N20: Monthly | O20: Implementation monitoring console | R20: Water point survey - Audit | S20: OREPA Focal Points & HANWASH M&E Manager | T20: Semi-annually | U20: Third party audit console (TBD) | V20: The reporting and system validation forms are the same, just different deployments carried out by different stakeholders. Reporting: PMO. Validation: Third party contractor.
